{"blocked": false, "observations": [{"count": 0, "dims": {"passports_all_11a": "-8", "resident_age_8d": "1", "ns_sec_10a": "-8"}}, {"count": 0, "dims": {"passports_all_11a": "-8", "resident_age_8d": "1", "ns_sec_10a": "1"}}, {"count": 0, "dims": {"passports_all_11a": "-8", "resident_age_8d": "1", "ns_sec_10a": "2"}}, {"count": 0, "dims": {"passports_all_11a": "-8", "resident_age_8d": "1", "ns_sec_10a": "3"}}, {"count": 0, "dims": {"passports_all_11a": "-8", "resident_age_8d": "1", "ns_sec_10a": "4"}}, {"count": 0, "dims": {"passports_all_11a": "-8", "resident_age_8d": "1", "ns_sec_10a": "5"}}, {"count": 0, "dims": {"passports_all_11a": "-8", "resident_age_8d": "1", "ns_sec_10a": "6"}}, {"count": 0, "dims": {"passports_all_11a": "-8", "resident_age_8d": "1", "ns_sec_10a": "7"}}, {"count": 0, "dims": {"passports_all_11a": "-8", "resident_age_8d": "1", "ns_sec_10a": "8"}}, {"count": 0, "dims": {"passports_all_11a": "-8", "resident_age_8d": "1", "ns_sec_10a": "9"}}, {"count": 0, "dims": {"passports_all_11a": "-8", "resident_age_8d": "2", "ns_sec_10a": "-8"}}, {"count": 0, "dims": {"passports_all_11a": "-8", "resident_age_8d": "2", "ns_sec_10a": "1"}}, {"count": 0, "dims": {"passports_all_11a": "-8", "resident_age_8d": "2", "ns_sec_10a": "2"}}, {"count": 0, "dims": {"passports_all_11a": "-8", "resident_age_8d": "2", "ns_sec_10a": "3"}}, {"count": 0, "dims": {"passports_all_11a": "-8", "resident_age_8d": "2", "ns_sec_10a": "4"}}, {"count": 0, "dims": {"passports_all_11a": "-8", "resident_age_8d": "2", "ns_sec_10a": "5"}}, {"count": 0, "dims": {"passports_all_11a": "-8", "resident_age_8d": "2", "ns_sec_10a": "6"}}, {"count": 0, "dims": {"passports_all_11a": "-8", "resident_age_8d": "2", "ns_sec_10a": "7"}}, {"count": 0, "dims": {"passports_all_11a": "-8", "resident_age_8d": "2", "ns_sec_10a": "8"}}, {"count": 0, "dims": {"passports_all_11a": "-8", "resident_age_8d": "2", "ns_sec_10a": "9"}}, {"count": 0, "dims": {"passports_all_11a": "-8", "resident_age_8d": "3", "ns_sec_10a": "-8"}}, {"count": 0, "dims": {"passports_all_11a": "-8", "resident_age_8d": "3", "ns_sec_10a": "1"}}, {"count": 0, "dims": {"passports_all_11a": "-8", "resident_age_8d": "3", "ns_sec_10a": "2"}}, {"count": 0, "dims": {"passports_all_11a": "-8", "resident_age_8d": "3", "ns_sec_10a": "3"}}, {"count": 0, "dims": {"passports_all_11a": "-8", "resident_age_8d": "3", "ns_sec_10a": "4"}}, {"count": 0, "dims": {"passports_all_11a": "-8", "resident_age_8d": "3", "ns_sec_10a": "5"}}, {"count": 0, "dims": {"passports_all_11a": "-8", "resident_age_8d": "3", "ns_sec_10a": "6"}}, {"count": 0, "dims": {"passports_all_11a": "-8", "resident_age_8d": "3", "ns_sec_10a": "7"}}, {"count": 0, "dims": {"passports_all_11a": "-8", "resident_age_8d": "3", "ns_sec_10a": "8"}}, {"count": 0, "dims": {"passports_all_11a": "-8", "resident_age_8d": "3", "ns_sec_10a": "9"}}, {"count": 0, "dims": {"passports_all_11a": "-8", "resident_age_8d": "4", "ns_sec_10a": "-8"}}, {"count": 0, "dims": {"passports_all_11a": "-8", "resident_age_8d": "4", "ns_sec_10a": "1"}}, {"count": 0, "dims": {"passports_all_11a": "-8", "resident_age_8d": "4", "ns_sec_10a": "2"}}, {"count": 0, "dims": {"passports_all_11a": "-8", "resident_age_8d": "4", "ns_sec_10a": "3"}}, {"count": 0, "dims": {"passports_all_11a": "-8", "resident_age_8d": "4", "ns_sec_10a": "4"}}, {"count": 0, "dims": {"passports_all_11a": "-8", "resident_age_8d": "4", "ns_sec_10a": "5"}}, {"count": 0, "dims": {"passports_all_11a": "-8", "resident_age_8d": "4", "ns_sec_10a": "6"}}, {"count": 0, "dims": {"passports_all_11a": "-8", "resident_age_8d": "4", "ns_sec_10a": "7"}}, {"count": 0, "dims": {"passports_all_11a": "-8", "resident_age_8d": "4", "ns_sec_10a": "8"}}, {"count": 0, "dims": {"passports_all_11a": "-8", "resident_age_8d": "4", "ns_sec_10a": "9"}}, {"count": 0, "dims": {"passports_all_11a": "-8", "resident_age_8d": "5", "ns_sec_10a": "-8"}}, {"count": 0, "dims": {"passports_all_11a": "-8", "resident_age_8d": "5", "ns_sec_10a": "1"}}, {"count": 0, "dims": {"passports_all_11a": "-8", "resident_age_8d": "5", "ns_sec_10a": "2"}}, {"count": 0, "dims": {"passports_all_11a": "-8", "resident_age_8d": "5", "ns_sec_10a": "3"}}, {"count": 0, "dims": {"passports_all_11a": "-8", "resident_age_8d": "5", "ns_sec_10a": "4"}}, {"count": 0, "dims": {"passports_all_11a": "-8", "resident_age_8d": "5", "ns_sec_10a": "5"}}, {"count": 0, "dims": {"passports_all_11a": "-8", "resident_age_8d": "5", "ns_sec_10a": "6"}}, {"count": 0, "dims": {"passports_all_11a": "-8", "resident_age_8d": "5", "ns_sec_10a": "7"}}, {"count": 0, "dims": {"passports_all_11a": "-8", "resident_age_8d": "5", "ns_sec_10a": "8"}}, {"count": 0, "dims": {"passports_all_11a": "-8", "resident_age_8d": "5", "ns_sec_10a": "9"}}, {"count": 0, "dims": {"passports_all_11a": "-8", "resident_age_8d": "6", "ns_sec_10a": "-8"}}, {"count": 0, "dims": {"passports_all_11a": "-8", "resident_age_8d": "6", "ns_sec_10a": "1"}}, {"count": 0, "dims": {"passports_all_11a": "-8", "resident_age_8d": "6", "ns_sec_10a": "2"}}, {"count": 0, "dims": {"passports_all_11a": "-8", "resident_age_8d": "6", "ns_sec_10a": "3"}}, {"count": 0, "dims": {"passports_all_11a": "-8", "resident_age_8d": "6", "ns_sec_10a": "4"}}, {"count": 0, "dims": {"passports_all_11a": "-8", "resident_age_8d": "6", "ns_sec_10a": "5"}}, {"count": 0, "dims": {"passports_all_11a": "-8", "resident_age_8d": "6", "ns_sec_10a": "6"}}, {"count": 0, "dims": {"passports_all_11a": "-8", "resident_age_8d": "6", "ns_sec_10a": "7"}}, {"count": 0, "dims": {"passports_all_11a": "-8", "resident_age_8d": "6", "ns_sec_10a": "8"}}, {"count": 0, "dims": {"passports_all_11a": "-8", "resident_age_8d": "6", "ns_sec_10a": "9"}}, {"count": 0, "dims": {"passports_all_11a": "-8", "resident_age_8d": "7", "ns_sec_10a": "-8"}}, {"count": 0, "dims": {"passports_all_11a": "-8", "resident_age_8d": "7", "ns_sec_10a": "1"}}, {"count": 0, "dims": {"passports_all_11a": "-8", "resident_age_8d": "7", "ns_sec_10a": "2"}}, {"count": 0, "dims": {"passports_all_11a": "-8", "resident_age_8d": "7", "ns_sec_10a": "3"}}, {"count": 0, "dims": {"passports_all_11a": "-8", "resident_age_8d": "7", "ns_sec_10a": "4"}}, {"count": 0, "dims": {"passports_all_11a": "-8", "resident_age_8d": "7", "ns_sec_10a": "5"}}, {"count": 0, "dims": {"passports_all_11a": "-8", "resident_age_8d": "7", "ns_sec_10a": "6"}}, {"count": 0, "dims": {"passports_all_11a": "-8", "resident_age_8d": "7", "ns_sec_10a": "7"}}, {"count": 0, "dims": {"passports_all_11a": "-8", "resident_age_8d": "7", "ns_sec_10a": "8"}}, {"count": 0, "dims": {"passports_all_11a": "-8", "resident_age_8d": "7", "ns_sec_10a": "9"}}, {"count": 0, "dims": {"passports_all_11a": "-8", "resident_age_8d": "8", "ns_sec_10a": "-8"}}, {"count": 0, "dims": {"passports_all_11a": "-8", "resident_age_8d": "8", "ns_sec_10a": "1"}}, {"count": 0, "dims": {"passports_all_11a": "-8", "resident_age_8d": "8", "ns_sec_10a": "2"}}, {"count": 0, "dims": {"passports_all_11a": "-8", "resident_age_8d": "8", "ns_sec_10a": "3"}}, {"count": 0, "dims": {"passports_all_11a": "-8", "resident_age_8d": "8", "ns_sec_10a": "4"}}, {"count": 0, "dims": {"passports_all_11a": "-8", "resident_age_8d": "8", "ns_sec_10a": "5"}}, {"count": 0, "dims": {"passports_all_11a": "-8", "resident_age_8d": "8", "ns_sec_10a": "6"}}, {"count": 0, "dims": {"passports_all_11a": "-8", "resident_age_8d": "8", "ns_sec_10a": "7"}}, {"count": 0, "dims": {"passports_all_11a": "-8", "resident_age_8d": "8", "ns_sec_10a": "8"}}, {"count": 0, "dims": {"passports_all_11a": "-8", "resident_age_8d": "8", "ns_sec_10a": "9"}}, {"count": 7595920, "dims": {"passports_all_11a": "1", "resident_age_8d": "1", "ns_sec_10a": "-8"}}, {"count": 0, "dims": {"passports_all_11a": "1", "resident_age_8d": "1", "ns_sec_10a": "1"}}, {"count": 0, "dims": {"passports_all_11a": "1", "resident_age_8d": "1", "ns_sec_10a": "2"}}, {"count": 0, "dims": {"passports_all_11a": "1", "resident_age_8d": "1", "ns_sec_10a": "3"}}, {"count": 0, "dims": {"passports_all_11a": "1", "resident_age_8d": "1", "ns_sec_10a": "4"}}, {"count": 0, "dims": {"passports_all_11a": "1", "resident_age_8d": "1", "ns_sec_10a": "5"}}, {"count": 0, "dims": {"passports_all_11a": "1", "resident_age_8d": "1", "ns_sec_10a": "6"}}, {"count": 0, "dims": {"passports_all_11a": "1", "resident_age_8d": "1", "ns_sec_10a": "7"}}, {"count": 0, "dims": {"passports_all_11a": "1", "resident_age_8d": "1", "ns_sec_10a": "8"}}, {"count": 0, "dims": {"passports_all_11a": "1", "resident_age_8d": "1", "ns_sec_10a": "9"}}, {"count": 0, "dims": {"passports_all_11a": "1", "resident_age_8d": "2", "ns_sec_10a": "-8"}}, {"count": 188899, "dims": {"passports_all_11a": "1", "resident_age_8d": "2", "ns_sec_10a": "1"}}, {"count": 419798, "dims": {"passports_all_11a": "1", "resident_age_8d": "2", "ns_sec_10a": "2"}}, {"count": 415818, "dims": {"passports_all_11a": "1", "resident_age_8d": "2", "ns_sec_10a": "3"}}, {"count": 137665, "dims": {"passports_all_11a": "1", "resident_age_8d": "2", "ns_sec_10a": "4"}}, {"count": 176579, "dims": {"passports_all_11a": "1", "resident_age_8d": "2", "ns_sec_10a": "5"}}, {"count": 467763, "dims": {"passports_all_11a": "1", "resident_age_8d": "2", "ns_sec_10a": "6"}}, {"count": 413556, "dims": {"passports_all_11a": "1", "resident_age_8d": "2", "ns_sec_10a": "7"}}, {"count": 292290, "dims": {"passports_all_11a": "1", "resident_age_8d": "2", "ns_sec_10a": "8"}}, {"count": 2550826, "dims": {"passports_all_11a": "1", "resident_age_8d": "2", "ns_sec_10a": "9"}}, {"count": 0, "dims": {"passports_all_11a": "1", "resident_age_8d": "3", "ns_sec_10a": "-8"}}, {"count": 1014558, "dims": {"passports_all_11a": "1", "resident_age_8d": "3", "ns_sec_10a": "1"}}, {"count": 1634599, "dims": {"passports_all_11a": "1", "resident_age_8d": "3", "ns_sec_10a": "2"}}, {"count": 818708, "dims": {"passports_all_11a": "1", "resident_age_8d": "3", "ns_sec_10a": "3"}}, {"count": 501598, "dims": {"passports_all_11a": "1", "resident_age_8d": "3", "ns_sec_10a": "4"}}, {"count": 351031, "dims": {"passports_all_11a": "1", "resident_age_8d": "3", "ns_sec_10a": "5"}}, {"count": 668256, "dims": {"passports_all_11a": "1", "resident_age_8d": "3", "ns_sec_10a": "6"}}, {"count": 537063, "dims": {"passports_all_11a": "1", "resident_age_8d": "3", "ns_sec_10a": "7"}}, {"count": 320735, "dims": {"passports_all_11a": "1", "resident_age_8d": "3", "ns_sec_10a": "8"}}, {"count": 175671, "dims": {"passports_all_11a": "1", "resident_age_8d": "3", "ns_sec_10a": "9"}}, {"count": 0, "dims": {"passports_all_11a": "1", "resident_age_8d": "4", "ns_sec_10a": "-8"}}, {"count": 1182080, "dims": {"passports_all_11a": "1", "resident_age_8d": "4", "ns_sec_10a": "1"}}, {"count": 1584136, "dims": {"passports_all_11a": "1", "resident_age_8d": "4", "ns_sec_10a": "2"}}, {"count": 701000, "dims": {"passports_all_11a": "1", "resident_age_8d": "4", "ns_sec_10a": "3"}}, {"count": 675004, "dims": {"passports_all_11a": "1", "resident_age_8d": "4", "ns_sec_10a": "4"}}, {"count": 308136, "dims": {"passports_all_11a": "1", "resident_age_8d": "4", "ns_sec_10a": "5"}}, {"count": 525283, "dims": {"passports_all_11a": "1", "resident_age_8d": "4", "ns_sec_10a": "6"}}, {"count": 475506, "dims": {"passports_all_11a": "1", "resident_age_8d": "4", "ns_sec_10a": "7"}}, {"count": 296191, "dims": {"passports_all_11a": "1", "resident_age_8d": "4", "ns_sec_10a": "8"}}, {"count": 65767, "dims": {"passports_all_11a": "1", "resident_age_8d": "4", "ns_sec_10a": "9"}}, {"count": 0, "dims": {"passports_all_11a": "1", "resident_age_8d": "5", "ns_sec_10a": "-8"}}, {"count": 1174946, "dims": {"passports_all_11a": "1", "resident_age_8d": "5", "ns_sec_10a": "1"}}, {"count": 1602300, "dims": {"passports_all_11a": "1", "resident_age_8d": "5", "ns_sec_10a": "2"}}, {"count": 814464, "dims": {"passports_all_11a": "1", "resident_age_8d": "5", "ns_sec_10a": "3"}}, {"count": 859921, "dims": {"passports_all_11a": "1", "resident_age_8d": "5", "ns_sec_10a": "4"}}, {"count": 353761, "dims": {"passports_all_11a": "1", "resident_age_8d": "5", "ns_sec_10a": "5"}}, {"count": 660535, "dims": {"passports_all_11a": "1", "resident_age_8d": "5", "ns_sec_10a": "6"}}, {"count": 649273, "dims": {"passports_all_11a": "1", "resident_age_8d": "5", "ns_sec_10a": "7"}}, {"count": 309991, "dims": {"passports_all_11a": "1", "resident_age_8d": "5", "ns_sec_10a": "8"}}, {"count": 36348, "dims": {"passports_all_11a": "1", "resident_age_8d": "5", "ns_sec_10a": "9"}}, {"count": 0, "dims": {"passports_all_11a": "1", "resident_age_8d": "6", "ns_sec_10a": "-8"}}, {"count": 921646, "dims": {"passports_all_11a": "1", "resident_age_8d": "6", "ns_sec_10a": "1"}}, {"count": 1378196, "dims": {"passports_all_11a": "1", "resident_age_8d": "6", "ns_sec_10a": "2"}}, {"count": 833741, "dims": {"passports_all_11a": "1", "resident_age_8d": "6", "ns_sec_10a": "3"}}, {"count": 883671, "dims": {"passports_all_11a": "1", "resident_age_8d": "6", "ns_sec_10a": "4"}}, {"count": 348192, "dims": {"passports_all_11a": "1", "resident_age_8d": "6", "ns_sec_10a": "5"}}, {"count": 794893, "dims": {"passports_all_11a": "1", "resident_age_8d": "6", "ns_sec_10a": "6"}}, {"count": 771783, "dims": {"passports_all_11a": "1", "resident_age_8d": "6", "ns_sec_10a": "7"}}, {"count": 358976, "dims": {"passports_all_11a": "1", "resident_age_8d": "6", "ns_sec_10a": "8"}}, {"count": 15268, "dims": {"passports_all_11a": "1", "resident_age_8d": "6", "ns_sec_10a": "9"}}, {"count": 0, "dims": {"passports_all_11a": "1", "resident_age_8d": "7", "ns_sec_10a": "-8"}}, {"count": 633504, "dims": {"passports_all_11a": "1", "resident_age_8d": "7", "ns_sec_10a": "1"}}, {"count": 1029694, "dims": {"passports_all_11a": "1", "resident_age_8d": "7", "ns_sec_10a": "2"}}, {"count": 641172, "dims": {"passports_all_11a": "1", "resident_age_8d": "7", "ns_sec_10a": "3"}}, {"count": 614847, "dims": {"passports_all_11a": "1", "resident_age_8d": "7", "ns_sec_10a": "4"}}, {"count": 252620, "dims": {"passports_all_11a": "1", "resident_age_8d": "7", "ns_sec_10a": "5"}}, {"count": 597540, "dims": {"passports_all_11a": "1", "resident_age_8d": "7", "ns_sec_10a": "6"}}, {"count": 564167, "dims": {"passports_all_11a": "1", "resident_age_8d": "7", "ns_sec_10a": "7"}}, {"count": 516593, "dims": {"passports_all_11a": "1", "resident_age_8d": "7", "ns_sec_10a": "8"}}, {"count": 4889, "dims": {"passports_all_11a": "1", "resident_age_8d": "7", "ns_sec_10a": "9"}}, {"count": 0, "dims": {"passports_all_11a": "1", "resident_age_8d": "8", "ns_sec_10a": "-8"}}, {"count": 404017, "dims": {"passports_all_11a": "1", "resident_age_8d": "8", "ns_sec_10a": "1"}}, {"count": 711732, "dims": {"passports_all_11a": "1", "resident_age_8d": "8", "ns_sec_10a": "2"}}, {"count": 478706, "dims": {"passports_all_11a": "1", "resident_age_8d": "8", "ns_sec_10a": "3"}}, {"count": 395617, "dims": {"passports_all_11a": "1", "resident_age_8d": "8", "ns_sec_10a": "4"}}, {"count": 204742, "dims": {"passports_all_11a": "1", "resident_age_8d": "8", "ns_sec_10a": "5"}}, {"count": 439035, "dims": {"passports_all_11a": "1", "resident_age_8d": "8", "ns_sec_10a": "6"}}, {"count": 432555, "dims": {"passports_all_11a": "1", "resident_age_8d": "8", "ns_sec_10a": "7"}}, {"count": 501028, "dims": {"passports_all_11a": "1", "resident_age_8d": "8", "ns_sec_10a": "8"}}, {"count": 3653, "dims": {"passports_all_11a": "1", "resident_age_8d": "8", "ns_sec_10a": "9"}}, {"count": 26429, "dims": {"passports_all_11a": "2", "resident_age_8d": "1", "ns_sec_10a": "-8"}}, {"count": 0, "dims": {"passports_all_11a": "2", "resident_age_8d": "1", "ns_sec_10a": "1"}}, {"count": 0, "dims": {"passports_all_11a": "2", "resident_age_8d": "1", "ns_sec_10a": "2"}}, {"count": 0, "dims": {"passports_all_11a": "2", "resident_age_8d": "1", "ns_sec_10a": "3"}}, {"count": 0, "dims": {"passports_all_11a": "2", "resident_age_8d": "1", "ns_sec_10a": "4"}}, {"count": 0, "dims": {"passports_all_11a": "2", "resident_age_8d": "1", "ns_sec_10a": "5"}}, {"count": 0, "dims": {"passports_all_11a": "2", "resident_age_8d": "1", "ns_sec_10a": "6"}}, {"count": 0, "dims": {"passports_all_11a": "2", "resident_age_8d": "1", "ns_sec_10a": "7"}}, {"count": 0, "dims": {"passports_all_11a": "2", "resident_age_8d": "1", "ns_sec_10a": "8"}}, {"count": 0, "dims": {"passports_all_11a": "2", "resident_age_8d": "1", "ns_sec_10a": "9"}}, {"count": 0, "dims": {"passports_all_11a": "2", "resident_age_8d": "2", "ns_sec_10a": "-8"}}, {"count": 1355, "dims": {"passports_all_11a": "2", "resident_age_8d": "2", "ns_sec_10a": "1"}}, {"count": 2926, "dims": {"passports_all_11a": "2", "resident_age_8d": "2", "ns_sec_10a": "2"}}, {"count": 1597, "dims": {"passports_all_11a": "2", "resident_age_8d": "2", "ns_sec_10a": "3"}}, {"count": 473, "dims": {"passports_all_11a": "2", "resident_age_8d": "2", "ns_sec_10a": "4"}}, {"count": 520, "dims": {"passports_all_11a": "2", "resident_age_8d": "2", "ns_sec_10a": "5"}}, {"count": 1464, "dims": {"passports_all_11a": "2", "resident_age_8d": "2", "ns_sec_10a": "6"}}, {"count": 1433, "dims": {"passports_all_11a": "2", "resident_age_8d": "2", "ns_sec_10a": "7"}}, {"count": 1325, "dims": {"passports_all_11a": "2", "resident_age_8d": "2", "ns_sec_10a": "8"}}, {"count": 19519, "dims": {"passports_all_11a": "2", "resident_age_8d": "2", "ns_sec_10a": "9"}}, {"count": 0, "dims": {"passports_all_11a": "2", "resident_age_8d": "3", "ns_sec_10a": "-8"}}, {"count": 13544, "dims": {"passports_all_11a": "2", "resident_age_8d": "3", "ns_sec_10a": "1"}}, {"count": 17857, "dims": {"passports_all_11a": "2", "resident_age_8d": "3", "ns_sec_10a": "2"}}, {"count": 4273, "dims": {"passports_all_11a": "2", "resident_age_8d": "3", "ns_sec_10a": "3"}}, {"count": 2767, "dims": {"passports_all_11a": "2", "resident_age_8d": "3", "ns_sec_10a": "4"}}, {"count": 1491, "dims": {"passports_all_11a": "2", "resident_age_8d": "3", "ns_sec_10a": "5"}}, {"count": 2325, "dims": {"passports_all_11a": "2", "resident_age_8d": "3", "ns_sec_10a": "6"}}, {"count": 2013, "dims": {"passports_all_11a": "2", "resident_age_8d": "3", "ns_sec_10a": "7"}}, {"count": 1391, "dims": {"passports_all_11a": "2", "resident_age_8d": "3", "ns_sec_10a": "8"}}, {"count": 2112, "dims": {"passports_all_11a": "2", "resident_age_8d": "3", "ns_sec_10a": "9"}}, {"count": 0, "dims": {"passports_all_11a": "2", "resident_age_8d": "4", "ns_sec_10a": "-8"}}, {"count": 15257, "dims": {"passports_all_11a": "2", "resident_age_8d": "4", "ns_sec_10a": "1"}}, {"count": 15899, "dims": {"passports_all_11a": "2", "resident_age_8d": "4", "ns_sec_10a": "2"}}, {"count": 4124, "dims": {"passports_all_11a": "2", "resident_age_8d": "4", "ns_sec_10a": "3"}}, {"count": 5076, "dims": {"passports_all_11a": "2", "resident_age_8d": "4", "ns_sec_10a": "4"}}, {"count": 1518, "dims": {"passports_all_11a": "2", "resident_age_8d": "4", "ns_sec_10a": "5"}}, {"count": 2380, "dims": {"passports_all_11a": "2", "resident_age_8d": "4", "ns_sec_10a": "6"}}, {"count": 2122, "dims": {"passports_all_11a": "2", "resident_age_8d": "4", "ns_sec_10a": "7"}}, {"count": 1863, "dims": {"passports_all_11a": "2", "resident_age_8d": "4", "ns_sec_10a": "8"}}, {"count": 683, "dims": {"passports_all_11a": "2", "resident_age_8d": "4", "ns_sec_10a": "9"}}, {"count": 0, "dims": {"passports_all_11a": "2", "resident_age_8d": "5", "ns_sec_10a": "-8"}}, {"count": 13417, "dims": {"passports_all_11a": "2", "resident_age_8d": "5", "ns_sec_10a": "1"}}, {"count": 15076, "dims": {"passports_all_11a": "2", "resident_age_8d": "5", "ns_sec_10a": "2"}}, {"count": 5414, "dims": {"passports_all_11a": "2", "resident_age_8d": "5", "ns_sec_10a": "3"}}, {"count": 7297, "dims": {"passports_all_11a": "2", "resident_age_8d": "5", "ns_sec_10a": "4"}}, {"count": 2084, "dims": {"passports_all_11a": "2", "resident_age_8d": "5", "ns_sec_10a": "5"}}, {"count": 3813, "dims": {"passports_all_11a": "2", "resident_age_8d": "5", "ns_sec_10a": "6"}}, {"count": 3467, "dims": {"passports_all_11a": "2", "resident_age_8d": "5", "ns_sec_10a": "7"}}, {"count": 2488, "dims": {"passports_all_11a": "2", "resident_age_8d": "5", "ns_sec_10a": "8"}}, {"count": 681, "dims": {"passports_all_11a": "2", "resident_age_8d": "5", "ns_sec_10a": "9"}}, {"count": 0, "dims": {"passports_all_11a": "2", "resident_age_8d": "6", "ns_sec_10a": "-8"}}, {"count": 9974, "dims": {"passports_all_11a": "2", "resident_age_8d": "6", "ns_sec_10a": "1"}}, {"count": 13332, "dims": {"passports_all_11a": "2", "resident_age_8d": "6", "ns_sec_10a": "2"}}, {"count": 6058, "dims": {"passports_all_11a": "2", "resident_age_8d": "6", "ns_sec_10a": "3"}}, {"count": 8274, "dims": {"passports_all_11a": "2", "resident_age_8d": "6", "ns_sec_10a": "4"}}, {"count": 2417, "dims": {"passports_all_11a": "2", "resident_age_8d": "6", "ns_sec_10a": "5"}}, {"count": 5432, "dims": {"passports_all_11a": "2", "resident_age_8d": "6", "ns_sec_10a": "6"}}, {"count": 5245, "dims": {"passports_all_11a": "2", "resident_age_8d": "6", "ns_sec_10a": "7"}}, {"count": 3388, "dims": {"passports_all_11a": "2", "resident_age_8d": "6", "ns_sec_10a": "8"}}, {"count": 213, "dims": {"passports_all_11a": "2", "resident_age_8d": "6", "ns_sec_10a": "9"}}, {"count": 0, "dims": {"passports_all_11a": "2", "resident_age_8d": "7", "ns_sec_10a": "-8"}}, {"count": 5270, "dims": {"passports_all_11a": "2", "resident_age_8d": "7", "ns_sec_10a": "1"}}, {"count": 10877, "dims": {"passports_all_11a": "2", "resident_age_8d": "7", "ns_sec_10a": "2"}}, {"count": 5687, "dims": {"passports_all_11a": "2", "resident_age_8d": "7", "ns_sec_10a": "3"}}, {"count": 8119, "dims": {"passports_all_11a": "2", "resident_age_8d": "7", "ns_sec_10a": "4"}}, {"count": 2792, "dims": {"passports_all_11a": "2", "resident_age_8d": "7", "ns_sec_10a": "5"}}, {"count": 7340, "dims": {"passports_all_11a": "2", "resident_age_8d": "7", "ns_sec_10a": "6"}}, {"count": 8064, "dims": {"passports_all_11a": "2", "resident_age_8d": "7", "ns_sec_10a": "7"}}, {"count": 6972, "dims": {"passports_all_11a": "2", "resident_age_8d": "7", "ns_sec_10a": "8"}}, {"count": 98, "dims": {"passports_all_11a": "2", "resident_age_8d": "7", "ns_sec_10a": "9"}}, {"count": 0, "dims": {"passports_all_11a": "2", "resident_age_8d": "8", "ns_sec_10a": "-8"}}, {"count": 2627, "dims": {"passports_all_11a": "2", "resident_age_8d": "8", "ns_sec_10a": "1"}}, {"count": 8249, "dims": {"passports_all_11a": "2", "resident_age_8d": "8", "ns_sec_10a": "2"}}, {"count": 4400, "dims": {"passports_all_11a": "2", "resident_age_8d": "8", "ns_sec_10a": "3"}}, {"count": 5450, "dims": {"passports_all_11a": "2", "resident_age_8d": "8", "ns_sec_10a": "4"}}, {"count": 2898, "dims": {"passports_all_11a": "2", "resident_age_8d": "8", "ns_sec_10a": "5"}}, {"count": 6887, "dims": {"passports_all_11a": "2", "resident_age_8d": "8", "ns_sec_10a": "6"}}, {"count": 9662, "dims": {"passports_all_11a": "2", "resident_age_8d": "8", "ns_sec_10a": "7"}}, {"count": 7460, "dims": {"passports_all_11a": "2", "resident_age_8d": "8", "ns_sec_10a": "8"}}, {"count": 67, "dims": {"passports_all_11a": "2", "resident_age_8d": "8", "ns_sec_10a": "9"}}, {"count": 583091, "dims": {"passports_all_11a": "3", "resident_age_8d": "1", "ns_sec_10a": "-8"}}, {"count": 0, "dims": {"passports_all_11a": "3", "resident_age_8d": "1", "ns_sec_10a": "1"}}, {"count": 0, "dims": {"passports_all_11a": "3", "resident_age_8d": "1", "ns_sec_10a": "2"}}, {"count": 0, "dims": {"passports_all_11a": "3", "resident_age_8d": "1", "ns_sec_10a": "3"}}, {"count": 0, "dims": {"passports_all_11a": "3", "resident_age_8d": "1", "ns_sec_10a": "4"}}, {"count": 0, "dims": {"passports_all_11a": "3", "resident_age_8d": "1", "ns_sec_10a": "5"}}, {"count": 0, "dims": {"passports_all_11a": "3", "resident_age_8d": "1", "ns_sec_10a": "6"}}, {"count": 0, "dims": {"passports_all_11a": "3", "resident_age_8d": "1", "ns_sec_10a": "7"}}, {"count": 0, "dims": {"passports_all_11a": "3", "resident_age_8d": "1", "ns_sec_10a": "8"}}, {"count": 0, "dims": {"passports_all_11a": "3", "resident_age_8d": "1", "ns_sec_10a": "9"}}, {"count": 0, "dims": {"passports_all_11a": "3", "resident_age_8d": "2", "ns_sec_10a": "-8"}}, {"count": 11688, "dims": {"passports_all_11a": "3", "resident_age_8d": "2", "ns_sec_10a": "1"}}, {"count": 22411, "dims": {"passports_all_11a": "3", "resident_age_8d": "2", "ns_sec_10a": "2"}}, {"count": 16834, "dims": {"passports_all_11a": "3", "resident_age_8d": "2", "ns_sec_10a": "3"}}, {"count": 21490, "dims": {"passports_all_11a": "3", "resident_age_8d": "2", "ns_sec_10a": "4"}}, {"count": 13981, "dims": {"passports_all_11a": "3", "resident_age_8d": "2", "ns_sec_10a": "5"}}, {"count": 27390, "dims": {"passports_all_11a": "3", "resident_age_8d": "2", "ns_sec_10a": "6"}}, {"count": 66201, "dims": {"passports_all_11a": "3", "resident_age_8d": "2", "ns_sec_10a": "7"}}, {"count": 23054, "dims": {"passports_all_11a": "3", "resident_age_8d": "2", "ns_sec_10a": "8"}}, {"count": 233153, "dims": {"passports_all_11a": "3", "resident_age_8d": "2", "ns_sec_10a": "9"}}, {"count": 0, "dims": {"passports_all_11a": "3", "resident_age_8d": "3", "ns_sec_10a": "-8"}}, {"count": 112135, "dims": {"passports_all_11a": "3", "resident_age_8d": "3", "ns_sec_10a": "1"}}, {"count": 153027, "dims": {"passports_all_11a": "3", "resident_age_8d": "3", "ns_sec_10a": "2"}}, {"count": 67146, "dims": {"passports_all_11a": "3", "resident_age_8d": "3", "ns_sec_10a": "3"}}, {"count": 110816, "dims": {"passports_all_11a": "3", "resident_age_8d": "3", "ns_sec_10a": "4"}}, {"count": 65138, "dims": {"passports_all_11a": "3", "resident_age_8d": "3", "ns_sec_10a": "5"}}, {"count": 83493, "dims": {"passports_all_11a": "3", "resident_age_8d": "3", "ns_sec_10a": "6"}}, {"count": 192005, "dims": {"passports_all_11a": "3", "resident_age_8d": "3", "ns_sec_10a": "7"}}, {"count": 29777, "dims": {"passports_all_11a": "3", "resident_age_8d": "3", "ns_sec_10a": "8"}}, {"count": 53796, "dims": {"passports_all_11a": "3", "resident_age_8d": "3", "ns_sec_10a": "9"}}, {"count": 0, "dims": {"passports_all_11a": "3", "resident_age_8d": "4", "ns_sec_10a": "-8"}}, {"count": 105829, "dims": {"passports_all_11a": "3", "resident_age_8d": "4", "ns_sec_10a": "1"}}, {"count": 132249, "dims": {"passports_all_11a": "3", "resident_age_8d": "4", "ns_sec_10a": "2"}}, {"count": 64023, "dims": {"passports_all_11a": "3", "resident_age_8d": "4", "ns_sec_10a": "3"}}, {"count": 139087, "dims": {"passports_all_11a": "3", "resident_age_8d": "4", "ns_sec_10a": "4"}}, {"count": 63159, "dims": {"passports_all_11a": "3", "resident_age_8d": "4", "ns_sec_10a": "5"}}, {"count": 84579, "dims": {"passports_all_11a": "3", "resident_age_8d": "4", "ns_sec_10a": "6"}}, {"count": 191659, "dims": {"passports_all_11a": "3", "resident_age_8d": "4", "ns_sec_10a": "7"}}, {"count": 31864, "dims": {"passports_all_11a": "3", "resident_age_8d": "4", "ns_sec_10a": "8"}}, {"count": 20916, "dims": {"passports_all_11a": "3", "resident_age_8d": "4", "ns_sec_10a": "9"}}, {"count": 0, "dims": {"passports_all_11a": "3", "resident_age_8d": "5", "ns_sec_10a": "-8"}}, {"count": 48852, "dims": {"passports_all_11a": "3", "resident_age_8d": "5", "ns_sec_10a": "1"}}, {"count": 57687, "dims": {"passports_all_11a": "3", "resident_age_8d": "5", "ns_sec_10a": "2"}}, {"count": 29588, "dims": {"passports_all_11a": "3", "resident_age_8d": "5", "ns_sec_10a": "3"}}, {"count": 85768, "dims": {"passports_all_11a": "3", "resident_age_8d": "5", "ns_sec_10a": "4"}}, {"count": 30884, "dims": {"passports_all_11a": "3", "resident_age_8d": "5", "ns_sec_10a": "5"}}, {"count": 50708, "dims": {"passports_all_11a": "3", "resident_age_8d": "5", "ns_sec_10a": "6"}}, {"count": 127874, "dims": {"passports_all_11a": "3", "resident_age_8d": "5", "ns_sec_10a": "7"}}, {"count": 23281, "dims": {"passports_all_11a": "3", "resident_age_8d": "5", "ns_sec_10a": "8"}}, {"count": 7807, "dims": {"passports_all_11a": "3", "resident_age_8d": "5", "ns_sec_10a": "9"}}, {"count": 0, "dims": {"passports_all_11a": "3", "resident_age_8d": "6", "ns_sec_10a": "-8"}}, {"count": 17373, "dims": {"passports_all_11a": "3", "resident_age_8d": "6", "ns_sec_10a": "1"}}, {"count": 21997, "dims": {"passports_all_11a": "3", "resident_age_8d": "6", "ns_sec_10a": "2"}}, {"count": 12766, "dims": {"passports_all_11a": "3", "resident_age_8d": "6", "ns_sec_10a": "3"}}, {"count": 37115, "dims": {"passports_all_11a": "3", "resident_age_8d": "6", "ns_sec_10a": "4"}}, {"count": 12084, "dims": {"passports_all_11a": "3", "resident_age_8d": "6", "ns_sec_10a": "5"}}, {"count": 25248, "dims": {"passports_all_11a": "3", "resident_age_8d": "6", "ns_sec_10a": "6"}}, {"count": 64404, "dims": {"passports_all_11a": "3", "resident_age_8d": "6", "ns_sec_10a": "7"}}, {"count": 16187, "dims": {"passports_all_11a": "3", "resident_age_8d": "6", "ns_sec_10a": "8"}}, {"count": 1592, "dims": {"passports_all_11a": "3", "resident_age_8d": "6", "ns_sec_10a": "9"}}, {"count": 0, "dims": {"passports_all_11a": "3", "resident_age_8d": "7", "ns_sec_10a": "-8"}}, {"count": 6859, "dims": {"passports_all_11a": "3", "resident_age_8d": "7", "ns_sec_10a": "1"}}, {"count": 10998, "dims": {"passports_all_11a": "3", "resident_age_8d": "7", "ns_sec_10a": "2"}}, {"count": 6596, "dims": {"passports_all_11a": "3", "resident_age_8d": "7", "ns_sec_10a": "3"}}, {"count": 12956, "dims": {"passports_all_11a": "3", "resident_age_8d": "7", "ns_sec_10a": "4"}}, {"count": 4047, "dims": {"passports_all_11a": "3", "resident_age_8d": "7", "ns_sec_10a": "5"}}, {"count": 8718, "dims": {"passports_all_11a": "3", "resident_age_8d": "7", "ns_sec_10a": "6"}}, {"count": 17888, "dims": {"passports_all_11a": "3", "resident_age_8d": "7", "ns_sec_10a": "7"}}, {"count": 13499, "dims": {"passports_all_11a": "3", "resident_age_8d": "7", "ns_sec_10a": "8"}}, {"count": 180, "dims": {"passports_all_11a": "3", "resident_age_8d": "7", "ns_sec_10a": "9"}}, {"count": 0, "dims": {"passports_all_11a": "3", "resident_age_8d": "8", "ns_sec_10a": "-8"}}, {"count": 3640, "dims": {"passports_all_11a": "3", "resident_age_8d": "8", "ns_sec_10a": "1"}}, {"count": 7213, "dims": {"passports_all_11a": "3", "resident_age_8d": "8", "ns_sec_10a": "2"}}, {"count": 4178, "dims": {"passports_all_11a": "3", "resident_age_8d": "8", "ns_sec_10a": "3"}}, {"count": 6548, "dims": {"passports_all_11a": "3", "resident_age_8d": "8", "ns_sec_10a": "4"}}, {"count": 2597, "dims": {"passports_all_11a": "3", "resident_age_8d": "8", "ns_sec_10a": "5"}}, {"count": 4901, "dims": {"passports_all_11a": "3", "resident_age_8d": "8", "ns_sec_10a": "6"}}, {"count": 8652, "dims": {"passports_all_11a": "3", "resident_age_8d": "8", "ns_sec_10a": "7"}}, {"count": 9682, "dims": {"passports_all_11a": "3", "resident_age_8d": "8", "ns_sec_10a": "8"}}, {"count": 78, "dims": {"passports_all_11a": "3", "resident_age_8d": "8", "ns_sec_10a": "9"}}, {"count": 22149, "dims": {"passports_all_11a": "4", "resident_age_8d": "1", "ns_sec_10a": "-8"}}, {"count": 0, "dims": {"passports_all_11a": "4", "resident_age_8d": "1", "ns_sec_10a": "1"}}, {"count": 0, "dims": {"passports_all_11a": "4", "resident_age_8d": "1", "ns_sec_10a": "2"}}, {"count": 0, "dims": {"passports_all_11a": "4", "resident_age_8d": "1", "ns_sec_10a": "3"}}, {"count": 0, "dims": {"passports_all_11a": "4", "resident_age_8d": "1", "ns_sec_10a": "4"}}, {"count": 0, "dims": {"passports_all_11a": "4", "resident_age_8d": "1", "ns_sec_10a": "5"}}, {"count": 0, "dims": {"passports_all_11a": "4", "resident_age_8d": "1", "ns_sec_10a": "6"}}, {"count": 0, "dims": {"passports_all_11a": "4", "resident_age_8d": "1", "ns_sec_10a": "7"}}, {"count": 0, "dims": {"passports_all_11a": "4", "resident_age_8d": "1", "ns_sec_10a": "8"}}, {"count": 0, "dims": {"passports_all_11a": "4", "resident_age_8d": "1", "ns_sec_10a": "9"}}, {"count": 0, "dims": {"passports_all_11a": "4", "resident_age_8d": "2", "ns_sec_10a": "-8"}}, {"count": 884, "dims": {"passports_all_11a": "4", "resident_age_8d": "2", "ns_sec_10a": "1"}}, {"count": 919, "dims": {"passports_all_11a": "4", "resident_age_8d": "2", "ns_sec_10a": "2"}}, {"count": 591, "dims": {"passports_all_11a": "4", "resident_age_8d": "2", "ns_sec_10a": "3"}}, {"count": 1509, "dims": {"passports_all_11a": "4", "resident_age_8d": "2", "ns_sec_10a": "4"}}, {"count": 365, "dims": {"passports_all_11a": "4", "resident_age_8d": "2", "ns_sec_10a": "5"}}, {"count": 813, "dims": {"passports_all_11a": "4", "resident_age_8d": "2", "ns_sec_10a": "6"}}, {"count": 1436, "dims": {"passports_all_11a": "4", "resident_age_8d": "2", "ns_sec_10a": "7"}}, {"count": 2550, "dims": {"passports_all_11a": "4", "resident_age_8d": "2", "ns_sec_10a": "8"}}, {"count": 12493, "dims": {"passports_all_11a": "4", "resident_age_8d": "2", "ns_sec_10a": "9"}}, {"count": 0, "dims": {"passports_all_11a": "4", "resident_age_8d": "3", "ns_sec_10a": "-8"}}, {"count": 10313, "dims": {"passports_all_11a": "4", "resident_age_8d": "3", "ns_sec_10a": "1"}}, {"count": 8114, "dims": {"passports_all_11a": "4", "resident_age_8d": "3", "ns_sec_10a": "2"}}, {"count": 3029, "dims": {"passports_all_11a": "4", "resident_age_8d": "3", "ns_sec_10a": "3"}}, {"count": 10303, "dims": {"passports_all_11a": "4", "resident_age_8d": "3", "ns_sec_10a": "4"}}, {"count": 2052, "dims": {"passports_all_11a": "4", "resident_age_8d": "3", "ns_sec_10a": "5"}}, {"count": 3294, "dims": {"passports_all_11a": "4", "resident_age_8d": "3", "ns_sec_10a": "6"}}, {"count": 5374, "dims": {"passports_all_11a": "4", "resident_age_8d": "3", "ns_sec_10a": "7"}}, {"count": 7729, "dims": {"passports_all_11a": "4", "resident_age_8d": "3", "ns_sec_10a": "8"}}, {"count": 3860, "dims": {"passports_all_11a": "4", "resident_age_8d": "3", "ns_sec_10a": "9"}}, {"count": 0, "dims": {"passports_all_11a": "4", "resident_age_8d": "4", "ns_sec_10a": "-8"}}, {"count": 7860, "dims": {"passports_all_11a": "4", "resident_age_8d": "4", "ns_sec_10a": "1"}}, {"count": 6374, "dims": {"passports_all_11a": "4", "resident_age_8d": "4", "ns_sec_10a": "2"}}, {"count": 2505, "dims": {"passports_all_11a": "4", "resident_age_8d": "4", "ns_sec_10a": "3"}}, {"count": 9305, "dims": {"passports_all_11a": "4", "resident_age_8d": "4", "ns_sec_10a": "4"}}, {"count": 2205, "dims": {"passports_all_11a": "4", "resident_age_8d": "4", "ns_sec_10a": "5"}}, {"count": 2886, "dims": {"passports_all_11a": "4", "resident_age_8d": "4", "ns_sec_10a": "6"}}, {"count": 4752, "dims": {"passports_all_11a": "4", "resident_age_8d": "4", "ns_sec_10a": "7"}}, {"count": 5140, "dims": {"passports_all_11a": "4", "resident_age_8d": "4", "ns_sec_10a": "8"}}, {"count": 815, "dims": {"passports_all_11a": "4", "resident_age_8d": "4", "ns_sec_10a": "9"}}, {"count": 0, "dims": {"passports_all_11a": "4", "resident_age_8d": "5", "ns_sec_10a": "-8"}}, {"count": 2930, "dims": {"passports_all_11a": "4", "resident_age_8d": "5", "ns_sec_10a": "1"}}, {"count": 2575, "dims": {"passports_all_11a": "4", "resident_age_8d": "5", "ns_sec_10a": "2"}}, {"count": 1142, "dims": {"passports_all_11a": "4", "resident_age_8d": "5", "ns_sec_10a": "3"}}, {"count": 4314, "dims": {"passports_all_11a": "4", "resident_age_8d": "5", "ns_sec_10a": "4"}}, {"count": 927, "dims": {"passports_all_11a": "4", "resident_age_8d": "5", "ns_sec_10a": "5"}}, {"count": 1485, "dims": {"passports_all_11a": "4", "resident_age_8d": "5", "ns_sec_10a": "6"}}, {"count": 2335, "dims": {"passports_all_11a": "4", "resident_age_8d": "5", "ns_sec_10a": "7"}}, {"count": 2358, "dims": {"passports_all_11a": "4", "resident_age_8d": "5", "ns_sec_10a": "8"}}, {"count": 210, "dims": {"passports_all_11a": "4", "resident_age_8d": "5", "ns_sec_10a": "9"}}, {"count": 0, "dims": {"passports_all_11a": "4", "resident_age_8d": "6", "ns_sec_10a": "-8"}}, {"count": 946, "dims": {"passports_all_11a": "4", "resident_age_8d": "6", "ns_sec_10a": "1"}}, {"count": 1083, "dims": {"passports_all_11a": "4", "resident_age_8d": "6", "ns_sec_10a": "2"}}, {"count": 473, "dims": {"passports_all_11a": "4", "resident_age_8d": "6", "ns_sec_10a": "3"}}, {"count": 1638, "dims": {"passports_all_11a": "4", "resident_age_8d": "6", "ns_sec_10a": "4"}}, {"count": 326, "dims": {"passports_all_11a": "4", "resident_age_8d": "6", "ns_sec_10a": "5"}}, {"count": 660, "dims": {"passports_all_11a": "4", "resident_age_8d": "6", "ns_sec_10a": "6"}}, {"count": 1127, "dims": {"passports_all_11a": "4", "resident_age_8d": "6", "ns_sec_10a": "7"}}, {"count": 1455, "dims": {"passports_all_11a": "4", "resident_age_8d": "6", "ns_sec_10a": "8"}}, {"count": 49, "dims": {"passports_all_11a": "4", "resident_age_8d": "6", "ns_sec_10a": "9"}}, {"count": 0, "dims": {"passports_all_11a": "4", "resident_age_8d": "7", "ns_sec_10a": "-8"}}, {"count": 482, "dims": {"passports_all_11a": "4", "resident_age_8d": "7", "ns_sec_10a": "1"}}, {"count": 675, "dims": {"passports_all_11a": "4", "resident_age_8d": "7", "ns_sec_10a": "2"}}, {"count": 338, "dims": {"passports_all_11a": "4", "resident_age_8d": "7", "ns_sec_10a": "3"}}, {"count": 541, "dims": {"passports_all_11a": "4", "resident_age_8d": "7", "ns_sec_10a": "4"}}, {"count": 126, "dims": {"passports_all_11a": "4", "resident_age_8d": "7", "ns_sec_10a": "5"}}, {"count": 334, "dims": {"passports_all_11a": "4", "resident_age_8d": "7", "ns_sec_10a": "6"}}, {"count": 320, "dims": {"passports_all_11a": "4", "resident_age_8d": "7", "ns_sec_10a": "7"}}, {"count": 826, "dims": {"passports_all_11a": "4", "resident_age_8d": "7", "ns_sec_10a": "8"}}, {"count": 6, "dims": {"passports_all_11a": "4", "resident_age_8d": "7", "ns_sec_10a": "9"}}, {"count": 0, "dims": {"passports_all_11a": "4", "resident_age_8d": "8", "ns_sec_10a": "-8"}}, {"count": 354, "dims": {"passports_all_11a": "4", "resident_age_8d": "8", "ns_sec_10a": "1"}}, {"count": 537, "dims": {"passports_all_11a": "4", "resident_age_8d": "8", "ns_sec_10a": "2"}}, {"count": 269, "dims": {"passports_all_11a": "4", "resident_age_8d": "8", "ns_sec_10a": "3"}}, {"count": 283, "dims": {"passports_all_11a": "4", "resident_age_8d": "8", "ns_sec_10a": "4"}}, {"count": 82, "dims": {"passports_all_11a": "4", "resident_age_8d": "8", "ns_sec_10a": "5"}}, {"count": 253, "dims": {"passports_all_11a": "4", "resident_age_8d": "8", "ns_sec_10a": "6"}}, {"count": 180, "dims": {"passports_all_11a": "4", "resident_age_8d": "8", "ns_sec_10a": "7"}}, {"count": 688, "dims": {"passports_all_11a": "4", "resident_age_8d": "8", "ns_sec_10a": "8"}}, {"count": 2, "dims": {"passports_all_11a": "4", "resident_age_8d": "8", "ns_sec_10a": "9"}}, {"count": 44732, "dims": {"passports_all_11a": "5", "resident_age_8d": "1", "ns_sec_10a": "-8"}}, {"count": 0, "dims": {"passports_all_11a": "5", "resident_age_8d": "1", "ns_sec_10a": "1"}}, {"count": 0, "dims": {"passports_all_11a": "5", "resident_age_8d": "1", "ns_sec_10a": "2"}}, {"count": 0, "dims": {"passports_all_11a": "5", "resident_age_8d": "1", "ns_sec_10a": "3"}}, {"count": 0, "dims": {"passports_all_11a": "5", "resident_age_8d": "1", "ns_sec_10a": "4"}}, {"count": 0, "dims": {"passports_all_11a": "5", "resident_age_8d": "1", "ns_sec_10a": "5"}}, {"count": 0, "dims": {"passports_all_11a": "5", "resident_age_8d": "1", "ns_sec_10a": "6"}}, {"count": 0, "dims": {"passports_all_11a": "5", "resident_age_8d": "1", "ns_sec_10a": "7"}}, {"count": 0, "dims": {"passports_all_11a": "5", "resident_age_8d": "1", "ns_sec_10a": "8"}}, {"count": 0, "dims": {"passports_all_11a": "5", "resident_age_8d": "1", "ns_sec_10a": "9"}}, {"count": 0, "dims": {"passports_all_11a": "5", "resident_age_8d": "2", "ns_sec_10a": "-8"}}, {"count": 1049, "dims": {"passports_all_11a": "5", "resident_age_8d": "2", "ns_sec_10a": "1"}}, {"count": 1707, "dims": {"passports_all_11a": "5", "resident_age_8d": "2", "ns_sec_10a": "2"}}, {"count": 1603, "dims": {"passports_all_11a": "5", "resident_age_8d": "2", "ns_sec_10a": "3"}}, {"count": 513, "dims": {"passports_all_11a": "5", "resident_age_8d": "2", "ns_sec_10a": "4"}}, {"count": 469, "dims": {"passports_all_11a": "5", "resident_age_8d": "2", "ns_sec_10a": "5"}}, {"count": 2624, "dims": {"passports_all_11a": "5", "resident_age_8d": "2", "ns_sec_10a": "6"}}, {"count": 2588, "dims": {"passports_all_11a": "5", "resident_age_8d": "2", "ns_sec_10a": "7"}}, {"count": 3458, "dims": {"passports_all_11a": "5", "resident_age_8d": "2", "ns_sec_10a": "8"}}, {"count": 30059, "dims": {"passports_all_11a": "5", "resident_age_8d": "2", "ns_sec_10a": "9"}}, {"count": 0, "dims": {"passports_all_11a": "5", "resident_age_8d": "3", "ns_sec_10a": "-8"}}, {"count": 14502, "dims": {"passports_all_11a": "5", "resident_age_8d": "3", "ns_sec_10a": "1"}}, {"count": 14890, "dims": {"passports_all_11a": "5", "resident_age_8d": "3", "ns_sec_10a": "2"}}, {"count": 7270, "dims": {"passports_all_11a": "5", "resident_age_8d": "3", "ns_sec_10a": "3"}}, {"count": 3929, "dims": {"passports_all_11a": "5", "resident_age_8d": "3", "ns_sec_10a": "4"}}, {"count": 2429, "dims": {"passports_all_11a": "5", "resident_age_8d": "3", "ns_sec_10a": "5"}}, {"count": 10344, "dims": {"passports_all_11a": "5", "resident_age_8d": "3", "ns_sec_10a": "6"}}, {"count": 6840, "dims": {"passports_all_11a": "5", "resident_age_8d": "3", "ns_sec_10a": "7"}}, {"count": 12298, "dims": {"passports_all_11a": "5", "resident_age_8d": "3", "ns_sec_10a": "8"}}, {"count": 14176, "dims": {"passports_all_11a": "5", "resident_age_8d": "3", "ns_sec_10a": "9"}}, {"count": 0, "dims": {"passports_all_11a": "5", "resident_age_8d": "4", "ns_sec_10a": "-8"}}, {"count": 14954, "dims": {"passports_all_11a": "5", "resident_age_8d": "4", "ns_sec_10a": "1"}}, {"count": 16550, "dims": {"passports_all_11a": "5", "resident_age_8d": "4", "ns_sec_10a": "2"}}, {"count": 9341, "dims": {"passports_all_11a": "5", "resident_age_8d": "4", "ns_sec_10a": "3"}}, {"count": 8385, "dims": {"passports_all_11a": "5", "resident_age_8d": "4", "ns_sec_10a": "4"}}, {"count": 4251, "dims": {"passports_all_11a": "5", "resident_age_8d": "4", "ns_sec_10a": "5"}}, {"count": 16781, "dims": {"passports_all_11a": "5", "resident_age_8d": "4", "ns_sec_10a": "6"}}, {"count": 11372, "dims": {"passports_all_11a": "5", "resident_age_8d": "4", "ns_sec_10a": "7"}}, {"count": 14082, "dims": {"passports_all_11a": "5", "resident_age_8d": "4", "ns_sec_10a": "8"}}, {"count": 8667, "dims": {"passports_all_11a": "5", "resident_age_8d": "4", "ns_sec_10a": "9"}}, {"count": 0, "dims": {"passports_all_11a": "5", "resident_age_8d": "5", "ns_sec_10a": "-8"}}, {"count": 5348, "dims": {"passports_all_11a": "5", "resident_age_8d": "5", "ns_sec_10a": "1"}}, {"count": 9596, "dims": {"passports_all_11a": "5", "resident_age_8d": "5", "ns_sec_10a": "2"}}, {"count": 5131, "dims": {"passports_all_11a": "5", "resident_age_8d": "5", "ns_sec_10a": "3"}}, {"count": 6536, "dims": {"passports_all_11a": "5", "resident_age_8d": "5", "ns_sec_10a": "4"}}, {"count": 3289, "dims": {"passports_all_11a": "5", "resident_age_8d": "5", "ns_sec_10a": "5"}}, {"count": 11620, "dims": {"passports_all_11a": "5", "resident_age_8d": "5", "ns_sec_10a": "6"}}, {"count": 8909, "dims": {"passports_all_11a": "5", "resident_age_8d": "5", "ns_sec_10a": "7"}}, {"count": 7009, "dims": {"passports_all_11a": "5", "resident_age_8d": "5", "ns_sec_10a": "8"}}, {"count": 3168, "dims": {"passports_all_11a": "5", "resident_age_8d": "5", "ns_sec_10a": "9"}}, {"count": 0, "dims": {"passports_all_11a": "5", "resident_age_8d": "6", "ns_sec_10a": "-8"}}, {"count": 1870, "dims": {"passports_all_11a": "5", "resident_age_8d": "6", "ns_sec_10a": "1"}}, {"count": 3869, "dims": {"passports_all_11a": "5", "resident_age_8d": "6", "ns_sec_10a": "2"}}, {"count": 1981, "dims": {"passports_all_11a": "5", "resident_age_8d": "6", "ns_sec_10a": "3"}}, {"count": 2888, "dims": {"passports_all_11a": "5", "resident_age_8d": "6", "ns_sec_10a": "4"}}, {"count": 1419, "dims": {"passports_all_11a": "5", "resident_age_8d": "6", "ns_sec_10a": "5"}}, {"count": 5099, "dims": {"passports_all_11a": "5", "resident_age_8d": "6", "ns_sec_10a": "6"}}, {"count": 3554, "dims": {"passports_all_11a": "5", "resident_age_8d": "6", "ns_sec_10a": "7"}}, {"count": 3311, "dims": {"passports_all_11a": "5", "resident_age_8d": "6", "ns_sec_10a": "8"}}, {"count": 511, "dims": {"passports_all_11a": "5", "resident_age_8d": "6", "ns_sec_10a": "9"}}, {"count": 0, "dims": {"passports_all_11a": "5", "resident_age_8d": "7", "ns_sec_10a": "-8"}}, {"count": 766, "dims": {"passports_all_11a": "5", "resident_age_8d": "7", "ns_sec_10a": "1"}}, {"count": 1363, "dims": {"passports_all_11a": "5", "resident_age_8d": "7", "ns_sec_10a": "2"}}, {"count": 641, "dims": {"passports_all_11a": "5", "resident_age_8d": "7", "ns_sec_10a": "3"}}, {"count": 1008, "dims": {"passports_all_11a": "5", "resident_age_8d": "7", "ns_sec_10a": "4"}}, {"count": 392, "dims": {"passports_all_11a": "5", "resident_age_8d": "7", "ns_sec_10a": "5"}}, {"count": 1496, "dims": {"passports_all_11a": "5", "resident_age_8d": "7", "ns_sec_10a": "6"}}, {"count": 1004, "dims": {"passports_all_11a": "5", "resident_age_8d": "7", "ns_sec_10a": "7"}}, {"count": 2474, "dims": {"passports_all_11a": "5", "resident_age_8d": "7", "ns_sec_10a": "8"}}, {"count": 44, "dims": {"passports_all_11a": "5", "resident_age_8d": "7", "ns_sec_10a": "9"}}, {"count": 0, "dims": {"passports_all_11a": "5", "resident_age_8d": "8", "ns_sec_10a": "-8"}}, {"count": 362, "dims": {"passports_all_11a": "5", "resident_age_8d": "8", "ns_sec_10a": "1"}}, {"count": 577, "dims": {"passports_all_11a": "5", "resident_age_8d": "8", "ns_sec_10a": "2"}}, {"count": 243, "dims": {"passports_all_11a": "5", "resident_age_8d": "8", "ns_sec_10a": "3"}}, {"count": 373, "dims": {"passports_all_11a": "5", "resident_age_8d": "8", "ns_sec_10a": "4"}}, {"count": 123, "dims": {"passports_all_11a": "5", "resident_age_8d": "8", "ns_sec_10a": "5"}}, {"count": 306, "dims": {"passports_all_11a": "5", "resident_age_8d": "8", "ns_sec_10a": "6"}}, {"count": 288, "dims": {"passports_all_11a": "5", "resident_age_8d": "8", "ns_sec_10a": "7"}}, {"count": 1862, "dims": {"passports_all_11a": "5", "resident_age_8d": "8", "ns_sec_10a": "8"}}, {"count": 10, "dims": {"passports_all_11a": "5", "resident_age_8d": "8", "ns_sec_10a": "9"}}, {"count": 124040, "dims": {"passports_all_11a": "6", "resident_age_8d": "1", "ns_sec_10a": "-8"}}, {"count": 0, "dims": {"passports_all_11a": "6", "resident_age_8d": "1", "ns_sec_10a": "1"}}, {"count": 0, "dims": {"passports_all_11a": "6", "resident_age_8d": "1", "ns_sec_10a": "2"}}, {"count": 0, "dims": {"passports_all_11a": "6", "resident_age_8d": "1", "ns_sec_10a": "3"}}, {"count": 0, "dims": {"passports_all_11a": "6", "resident_age_8d": "1", "ns_sec_10a": "4"}}, {"count": 0, "dims": {"passports_all_11a": "6", "resident_age_8d": "1", "ns_sec_10a": "5"}}, {"count": 0, "dims": {"passports_all_11a": "6", "resident_age_8d": "1", "ns_sec_10a": "6"}}, {"count": 0, "dims": {"passports_all_11a": "6", "resident_age_8d": "1", "ns_sec_10a": "7"}}, {"count": 0, "dims": {"passports_all_11a": "6", "resident_age_8d": "1", "ns_sec_10a": "8"}}, {"count": 0, "dims": {"passports_all_11a": "6", "resident_age_8d": "1", "ns_sec_10a": "9"}}, {"count": 0, "dims": {"passports_all_11a": "6", "resident_age_8d": "2", "ns_sec_10a": "-8"}}, {"count": 3449, "dims": {"passports_all_11a": "6", "resident_age_8d": "2", "ns_sec_10a": "1"}}, {"count": 3916, "dims": {"passports_all_11a": "6", "resident_age_8d": "2", "ns_sec_10a": "2"}}, {"count": 3496, "dims": {"passports_all_11a": "6", "resident_age_8d": "2", "ns_sec_10a": "3"}}, {"count": 1318, "dims": {"passports_all_11a": "6", "resident_age_8d": "2", "ns_sec_10a": "4"}}, {"count": 1252, "dims": {"passports_all_11a": "6", "resident_age_8d": "2", "ns_sec_10a": "5"}}, {"count": 4386, "dims": {"passports_all_11a": "6", "resident_age_8d": "2", "ns_sec_10a": "6"}}, {"count": 5200, "dims": {"passports_all_11a": "6", "resident_age_8d": "2", "ns_sec_10a": "7"}}, {"count": 13567, "dims": {"passports_all_11a": "6", "resident_age_8d": "2", "ns_sec_10a": "8"}}, {"count": 114930, "dims": {"passports_all_11a": "6", "resident_age_8d": "2", "ns_sec_10a": "9"}}, {"count": 0, "dims": {"passports_all_11a": "6", "resident_age_8d": "3", "ns_sec_10a": "-8"}}, {"count": 56430, "dims": {"passports_all_11a": "6", "resident_age_8d": "3", "ns_sec_10a": "1"}}, {"count": 60549, "dims": {"passports_all_11a": "6", "resident_age_8d": "3", "ns_sec_10a": "2"}}, {"count": 19579, "dims": {"passports_all_11a": "6", "resident_age_8d": "3", "ns_sec_10a": "3"}}, {"count": 17362, "dims": {"passports_all_11a": "6", "resident_age_8d": "3", "ns_sec_10a": "4"}}, {"count": 8655, "dims": {"passports_all_11a": "6", "resident_age_8d": "3", "ns_sec_10a": "5"}}, {"count": 28067, "dims": {"passports_all_11a": "6", "resident_age_8d": "3", "ns_sec_10a": "6"}}, {"count": 26653, "dims": {"passports_all_11a": "6", "resident_age_8d": "3", "ns_sec_10a": "7"}}, {"count": 62275, "dims": {"passports_all_11a": "6", "resident_age_8d": "3", "ns_sec_10a": "8"}}, {"count": 49624, "dims": {"passports_all_11a": "6", "resident_age_8d": "3", "ns_sec_10a": "9"}}, {"count": 0, "dims": {"passports_all_11a": "6", "resident_age_8d": "4", "ns_sec_10a": "-8"}}, {"count": 53515, "dims": {"passports_all_11a": "6", "resident_age_8d": "4", "ns_sec_10a": "1"}}, {"count": 39569, "dims": {"passports_all_11a": "6", "resident_age_8d": "4", "ns_sec_10a": "2"}}, {"count": 17176, "dims": {"passports_all_11a": "6", "resident_age_8d": "4", "ns_sec_10a": "3"}}, {"count": 24947, "dims": {"passports_all_11a": "6", "resident_age_8d": "4", "ns_sec_10a": "4"}}, {"count": 11885, "dims": {"passports_all_11a": "6", "resident_age_8d": "4", "ns_sec_10a": "5"}}, {"count": 26235, "dims": {"passports_all_11a": "6", "resident_age_8d": "4", "ns_sec_10a": "6"}}, {"count": 26867, "dims": {"passports_all_11a": "6", "resident_age_8d": "4", "ns_sec_10a": "7"}}, {"count": 53965, "dims": {"passports_all_11a": "6", "resident_age_8d": "4", "ns_sec_10a": "8"}}, {"count": 8021, "dims": {"passports_all_11a": "6", "resident_age_8d": "4", "ns_sec_10a": "9"}}, {"count": 0, "dims": {"passports_all_11a": "6", "resident_age_8d": "5", "ns_sec_10a": "-8"}}, {"count": 13241, "dims": {"passports_all_11a": "6", "resident_age_8d": "5", "ns_sec_10a": "1"}}, {"count": 12120, "dims": {"passports_all_11a": "6", "resident_age_8d": "5", "ns_sec_10a": "2"}}, {"count": 6728, "dims": {"passports_all_11a": "6", "resident_age_8d": "5", "ns_sec_10a": "3"}}, {"count": 12674, "dims": {"passports_all_11a": "6", "resident_age_8d": "5", "ns_sec_10a": "4"}}, {"count": 7268, "dims": {"passports_all_11a": "6", "resident_age_8d": "5", "ns_sec_10a": "5"}}, {"count": 12493, "dims": {"passports_all_11a": "6", "resident_age_8d": "5", "ns_sec_10a": "6"}}, {"count": 16615, "dims": {"passports_all_11a": "6", "resident_age_8d": "5", "ns_sec_10a": "7"}}, {"count": 22660, "dims": {"passports_all_11a": "6", "resident_age_8d": "5", "ns_sec_10a": "8"}}, {"count": 1318, "dims": {"passports_all_11a": "6", "resident_age_8d": "5", "ns_sec_10a": "9"}}, {"count": 0, "dims": {"passports_all_11a": "6", "resident_age_8d": "6", "ns_sec_10a": "-8"}}, {"count": 3858, "dims": {"passports_all_11a": "6", "resident_age_8d": "6", "ns_sec_10a": "1"}}, {"count": 4360, "dims": {"passports_all_11a": "6", "resident_age_8d": "6", "ns_sec_10a": "2"}}, {"count": 2739, "dims": {"passports_all_11a": "6", "resident_age_8d": "6", "ns_sec_10a": "3"}}, {"count": 5717, "dims": {"passports_all_11a": "6", "resident_age_8d": "6", "ns_sec_10a": "4"}}, {"count": 2958, "dims": {"passports_all_11a": "6", "resident_age_8d": "6", "ns_sec_10a": "5"}}, {"count": 6448, "dims": {"passports_all_11a": "6", "resident_age_8d": "6", "ns_sec_10a": "6"}}, {"count": 9431, "dims": {"passports_all_11a": "6", "resident_age_8d": "6", "ns_sec_10a": "7"}}, {"count": 14669, "dims": {"passports_all_11a": "6", "resident_age_8d": "6", "ns_sec_10a": "8"}}, {"count": 205, "dims": {"passports_all_11a": "6", "resident_age_8d": "6", "ns_sec_10a": "9"}}, {"count": 0, "dims": {"passports_all_11a": "6", "resident_age_8d": "7", "ns_sec_10a": "-8"}}, {"count": 1836, "dims": {"passports_all_11a": "6", "resident_age_8d": "7", "ns_sec_10a": "1"}}, {"count": 2812, "dims": {"passports_all_11a": "6", "resident_age_8d": "7", "ns_sec_10a": "2"}}, {"count": 1491, "dims": {"passports_all_11a": "6", "resident_age_8d": "7", "ns_sec_10a": "3"}}, {"count": 2496, "dims": {"passports_all_11a": "6", "resident_age_8d": "7", "ns_sec_10a": "4"}}, {"count": 933, "dims": {"passports_all_11a": "6", "resident_age_8d": "7", "ns_sec_10a": "5"}}, {"count": 2421, "dims": {"passports_all_11a": "6", "resident_age_8d": "7", "ns_sec_10a": "6"}}, {"count": 4232, "dims": {"passports_all_11a": "6", "resident_age_8d": "7", "ns_sec_10a": "7"}}, {"count": 15580, "dims": {"passports_all_11a": "6", "resident_age_8d": "7", "ns_sec_10a": "8"}}, {"count": 52, "dims": {"passports_all_11a": "6", "resident_age_8d": "7", "ns_sec_10a": "9"}}, {"count": 0, "dims": {"passports_all_11a": "6", "resident_age_8d": "8", "ns_sec_10a": "-8"}}, {"count": 1082, "dims": {"passports_all_11a": "6", "resident_age_8d": "8", "ns_sec_10a": "1"}}, {"count": 1272, "dims": {"passports_all_11a": "6", "resident_age_8d": "8", "ns_sec_10a": "2"}}, {"count": 777, "dims": {"passports_all_11a": "6", "resident_age_8d": "8", "ns_sec_10a": "3"}}, {"count": 958, "dims": {"passports_all_11a": "6", "resident_age_8d": "8", "ns_sec_10a": "4"}}, {"count": 344, "dims": {"passports_all_11a": "6", "resident_age_8d": "8", "ns_sec_10a": "5"}}, {"count": 874, "dims": {"passports_all_11a": "6", "resident_age_8d": "8", "ns_sec_10a": "6"}}, {"count": 2553, "dims": {"passports_all_11a": "6", "resident_age_8d": "8", "ns_sec_10a": "7"}}, {"count": 14050, "dims": {"passports_all_11a": "6", "resident_age_8d": "8", "ns_sec_10a": "8"}}, {"count": 27, "dims": {"passports_all_11a": "6", "resident_age_8d": "8", "ns_sec_10a": "9"}}, {"count": 31751, "dims": {"passports_all_11a": "7", "resident_age_8d": "1", "ns_sec_10a": "-8"}}, {"count": 0, "dims": {"passports_all_11a": "7", "resident_age_8d": "1", "ns_sec_10a": "1"}}, {"count": 0, "dims": {"passports_all_11a": "7", "resident_age_8d": "1", "ns_sec_10a": "2"}}, {"count": 0, "dims": {"passports_all_11a": "7", "resident_age_8d": "1", "ns_sec_10a": "3"}}, {"count": 0, "dims": {"passports_all_11a": "7", "resident_age_8d": "1", "ns_sec_10a": "4"}}, {"count": 0, "dims": {"passports_all_11a": "7", "resident_age_8d": "1", "ns_sec_10a": "5"}}, {"count": 0, "dims": {"passports_all_11a": "7", "resident_age_8d": "1", "ns_sec_10a": "6"}}, {"count": 0, "dims": {"passports_all_11a": "7", "resident_age_8d": "1", "ns_sec_10a": "7"}}, {"count": 0, "dims": {"passports_all_11a": "7", "resident_age_8d": "1", "ns_sec_10a": "8"}}, {"count": 0, "dims": {"passports_all_11a": "7", "resident_age_8d": "1", "ns_sec_10a": "9"}}, {"count": 0, "dims": {"passports_all_11a": "7", "resident_age_8d": "2", "ns_sec_10a": "-8"}}, {"count": 1185, "dims": {"passports_all_11a": "7", "resident_age_8d": "2", "ns_sec_10a": "1"}}, {"count": 2129, "dims": {"passports_all_11a": "7", "resident_age_8d": "2", "ns_sec_10a": "2"}}, {"count": 2021, "dims": {"passports_all_11a": "7", "resident_age_8d": "2", "ns_sec_10a": "3"}}, {"count": 1090, "dims": {"passports_all_11a": "7", "resident_age_8d": "2", "ns_sec_10a": "4"}}, {"count": 639, "dims": {"passports_all_11a": "7", "resident_age_8d": "2", "ns_sec_10a": "5"}}, {"count": 1494, "dims": {"passports_all_11a": "7", "resident_age_8d": "2", "ns_sec_10a": "6"}}, {"count": 2209, "dims": {"passports_all_11a": "7", "resident_age_8d": "2", "ns_sec_10a": "7"}}, {"count": 2329, "dims": {"passports_all_11a": "7", "resident_age_8d": "2", "ns_sec_10a": "8"}}, {"count": 16156, "dims": {"passports_all_11a": "7", "resident_age_8d": "2", "ns_sec_10a": "9"}}, {"count": 0, "dims": {"passports_all_11a": "7", "resident_age_8d": "3", "ns_sec_10a": "-8"}}, {"count": 18167, "dims": {"passports_all_11a": "7", "resident_age_8d": "3", "ns_sec_10a": "1"}}, {"count": 17517, "dims": {"passports_all_11a": "7", "resident_age_8d": "3", "ns_sec_10a": "2"}}, {"count": 6728, "dims": {"passports_all_11a": "7", "resident_age_8d": "3", "ns_sec_10a": "3"}}, {"count": 5774, "dims": {"passports_all_11a": "7", "resident_age_8d": "3", "ns_sec_10a": "4"}}, {"count": 2729, "dims": {"passports_all_11a": "7", "resident_age_8d": "3", "ns_sec_10a": "5"}}, {"count": 4735, "dims": {"passports_all_11a": "7", "resident_age_8d": "3", "ns_sec_10a": "6"}}, {"count": 6466, "dims": {"passports_all_11a": "7", "resident_age_8d": "3", "ns_sec_10a": "7"}}, {"count": 4956, "dims": {"passports_all_11a": "7", "resident_age_8d": "3", "ns_sec_10a": "8"}}, {"count": 9163, "dims": {"passports_all_11a": "7", "resident_age_8d": "3", "ns_sec_10a": "9"}}, {"count": 0, "dims": {"passports_all_11a": "7", "resident_age_8d": "4", "ns_sec_10a": "-8"}}, {"count": 18372, "dims": {"passports_all_11a": "7", "resident_age_8d": "4", "ns_sec_10a": "1"}}, {"count": 15871, "dims": {"passports_all_11a": "7", "resident_age_8d": "4", "ns_sec_10a": "2"}}, {"count": 5845, "dims": {"passports_all_11a": "7", "resident_age_8d": "4", "ns_sec_10a": "3"}}, {"count": 8388, "dims": {"passports_all_11a": "7", "resident_age_8d": "4", "ns_sec_10a": "4"}}, {"count": 2957, "dims": {"passports_all_11a": "7", "resident_age_8d": "4", "ns_sec_10a": "5"}}, {"count": 5290, "dims": {"passports_all_11a": "7", "resident_age_8d": "4", "ns_sec_10a": "6"}}, {"count": 7257, "dims": {"passports_all_11a": "7", "resident_age_8d": "4", "ns_sec_10a": "7"}}, {"count": 4919, "dims": {"passports_all_11a": "7", "resident_age_8d": "4", "ns_sec_10a": "8"}}, {"count": 2514, "dims": {"passports_all_11a": "7", "resident_age_8d": "4", "ns_sec_10a": "9"}}, {"count": 0, "dims": {"passports_all_11a": "7", "resident_age_8d": "5", "ns_sec_10a": "-8"}}, {"count": 9018, "dims": {"passports_all_11a": "7", "resident_age_8d": "5", "ns_sec_10a": "1"}}, {"count": 8823, "dims": {"passports_all_11a": "7", "resident_age_8d": "5", "ns_sec_10a": "2"}}, {"count": 3500, "dims": {"passports_all_11a": "7", "resident_age_8d": "5", "ns_sec_10a": "3"}}, {"count": 5939, "dims": {"passports_all_11a": "7", "resident_age_8d": "5", "ns_sec_10a": "4"}}, {"count": 1890, "dims": {"passports_all_11a": "7", "resident_age_8d": "5", "ns_sec_10a": "5"}}, {"count": 4443, "dims": {"passports_all_11a": "7", "resident_age_8d": "5", "ns_sec_10a": "6"}}, {"count": 6017, "dims": {"passports_all_11a": "7", "resident_age_8d": "5", "ns_sec_10a": "7"}}, {"count": 3442, "dims": {"passports_all_11a": "7", "resident_age_8d": "5", "ns_sec_10a": "8"}}, {"count": 827, "dims": {"passports_all_11a": "7", "resident_age_8d": "5", "ns_sec_10a": "9"}}, {"count": 0, "dims": {"passports_all_11a": "7", "resident_age_8d": "6", "ns_sec_10a": "-8"}}, {"count": 4731, "dims": {"passports_all_11a": "7", "resident_age_8d": "6", "ns_sec_10a": "1"}}, {"count": 5335, "dims": {"passports_all_11a": "7", "resident_age_8d": "6", "ns_sec_10a": "2"}}, {"count": 2406, "dims": {"passports_all_11a": "7", "resident_age_8d": "6", "ns_sec_10a": "3"}}, {"count": 3749, "dims": {"passports_all_11a": "7", "resident_age_8d": "6", "ns_sec_10a": "4"}}, {"count": 1108, "dims": {"passports_all_11a": "7", "resident_age_8d": "6", "ns_sec_10a": "5"}}, {"count": 2991, "dims": {"passports_all_11a": "7", "resident_age_8d": "6", "ns_sec_10a": "6"}}, {"count": 3810, "dims": {"passports_all_11a": "7", "resident_age_8d": "6", "ns_sec_10a": "7"}}, {"count": 2296, "dims": {"passports_all_11a": "7", "resident_age_8d": "6", "ns_sec_10a": "8"}}, {"count": 220, "dims": {"passports_all_11a": "7", "resident_age_8d": "6", "ns_sec_10a": "9"}}, {"count": 0, "dims": {"passports_all_11a": "7", "resident_age_8d": "7", "ns_sec_10a": "-8"}}, {"count": 2343, "dims": {"passports_all_11a": "7", "resident_age_8d": "7", "ns_sec_10a": "1"}}, {"count": 3263, "dims": {"passports_all_11a": "7", "resident_age_8d": "7", "ns_sec_10a": "2"}}, {"count": 1435, "dims": {"passports_all_11a": "7", "resident_age_8d": "7", "ns_sec_10a": "3"}}, {"count": 1867, "dims": {"passports_all_11a": "7", "resident_age_8d": "7", "ns_sec_10a": "4"}}, {"count": 493, "dims": {"passports_all_11a": "7", "resident_age_8d": "7", "ns_sec_10a": "5"}}, {"count": 1494, "dims": {"passports_all_11a": "7", "resident_age_8d": "7", "ns_sec_10a": "6"}}, {"count": 1405, "dims": {"passports_all_11a": "7", "resident_age_8d": "7", "ns_sec_10a": "7"}}, {"count": 1816, "dims": {"passports_all_11a": "7", "resident_age_8d": "7", "ns_sec_10a": "8"}}, {"count": 71, "dims": {"passports_all_11a": "7", "resident_age_8d": "7", "ns_sec_10a": "9"}}, {"count": 0, "dims": {"passports_all_11a": "7", "resident_age_8d": "8", "ns_sec_10a": "-8"}}, {"count": 1287, "dims": {"passports_all_11a": "7", "resident_age_8d": "8", "ns_sec_10a": "1"}}, {"count": 1655, "dims": {"passports_all_11a": "7", "resident_age_8d": "8", "ns_sec_10a": "2"}}, {"count": 599, "dims": {"passports_all_11a": "7", "resident_age_8d": "8", "ns_sec_10a": "3"}}, {"count": 720, "dims": {"passports_all_11a": "7", "resident_age_8d": "8", "ns_sec_10a": "4"}}, {"count": 204, "dims": {"passports_all_11a": "7", "resident_age_8d": "8", "ns_sec_10a": "5"}}, {"count": 561, "dims": {"passports_all_11a": "7", "resident_age_8d": "8", "ns_sec_10a": "6"}}, {"count": 554, "dims": {"passports_all_11a": "7", "resident_age_8d": "8", "ns_sec_10a": "7"}}, {"count": 1284, "dims": {"passports_all_11a": "7", "resident_age_8d": "8", "ns_sec_10a": "8"}}, {"count": 16, "dims": {"passports_all_11a": "7", "resident_age_8d": "8", "ns_sec_10a": "9"}}, {"count": 4137, "dims": {"passports_all_11a": "8", "resident_age_8d": "1", "ns_sec_10a": "-8"}}, {"count": 0, "dims": {"passports_all_11a": "8", "resident_age_8d": "1", "ns_sec_10a": "1"}}, {"count": 0, "dims": {"passports_all_11a": "8", "resident_age_8d": "1", "ns_sec_10a": "2"}}, {"count": 0, "dims": {"passports_all_11a": "8", "resident_age_8d": "1", "ns_sec_10a": "3"}}, {"count": 0, "dims": {"passports_all_11a": "8", "resident_age_8d": "1", "ns_sec_10a": "4"}}, {"count": 0, "dims": {"passports_all_11a": "8", "resident_age_8d": "1", "ns_sec_10a": "5"}}, {"count": 0, "dims": {"passports_all_11a": "8", "resident_age_8d": "1", "ns_sec_10a": "6"}}, {"count": 0, "dims": {"passports_all_11a": "8", "resident_age_8d": "1", "ns_sec_10a": "7"}}, {"count": 0, "dims": {"passports_all_11a": "8", "resident_age_8d": "1", "ns_sec_10a": "8"}}, {"count": 0, "dims": {"passports_all_11a": "8", "resident_age_8d": "1", "ns_sec_10a": "9"}}, {"count": 0, "dims": {"passports_all_11a": "8", "resident_age_8d": "2", "ns_sec_10a": "-8"}}, {"count": 307, "dims": {"passports_all_11a": "8", "resident_age_8d": "2", "ns_sec_10a": "1"}}, {"count": 616, "dims": {"passports_all_11a": "8", "resident_age_8d": "2", "ns_sec_10a": "2"}}, {"count": 570, "dims": {"passports_all_11a": "8", "resident_age_8d": "2", "ns_sec_10a": "3"}}, {"count": 103, "dims": {"passports_all_11a": "8", "resident_age_8d": "2", "ns_sec_10a": "4"}}, {"count": 113, "dims": {"passports_all_11a": "8", "resident_age_8d": "2", "ns_sec_10a": "5"}}, {"count": 294, "dims": {"passports_all_11a": "8", "resident_age_8d": "2", "ns_sec_10a": "6"}}, {"count": 424, "dims": {"passports_all_11a": "8", "resident_age_8d": "2", "ns_sec_10a": "7"}}, {"count": 268, "dims": {"passports_all_11a": "8", "resident_age_8d": "2", "ns_sec_10a": "8"}}, {"count": 2016, "dims": {"passports_all_11a": "8", "resident_age_8d": "2", "ns_sec_10a": "9"}}, {"count": 0, "dims": {"passports_all_11a": "8", "resident_age_8d": "3", "ns_sec_10a": "-8"}}, {"count": 9183, "dims": {"passports_all_11a": "8", "resident_age_8d": "3", "ns_sec_10a": "1"}}, {"count": 8139, "dims": {"passports_all_11a": "8", "resident_age_8d": "3", "ns_sec_10a": "2"}}, {"count": 2218, "dims": {"passports_all_11a": "8", "resident_age_8d": "3", "ns_sec_10a": "3"}}, {"count": 987, "dims": {"passports_all_11a": "8", "resident_age_8d": "3", "ns_sec_10a": "4"}}, {"count": 708, "dims": {"passports_all_11a": "8", "resident_age_8d": "3", "ns_sec_10a": "5"}}, {"count": 840, "dims": {"passports_all_11a": "8", "resident_age_8d": "3", "ns_sec_10a": "6"}}, {"count": 836, "dims": {"passports_all_11a": "8", "resident_age_8d": "3", "ns_sec_10a": "7"}}, {"count": 403, "dims": {"passports_all_11a": "8", "resident_age_8d": "3", "ns_sec_10a": "8"}}, {"count": 876, "dims": {"passports_all_11a": "8", "resident_age_8d": "3", "ns_sec_10a": "9"}}, {"count": 0, "dims": {"passports_all_11a": "8", "resident_age_8d": "4", "ns_sec_10a": "-8"}}, {"count": 6914, "dims": {"passports_all_11a": "8", "resident_age_8d": "4", "ns_sec_10a": "1"}}, {"count": 5428, "dims": {"passports_all_11a": "8", "resident_age_8d": "4", "ns_sec_10a": "2"}}, {"count": 1287, "dims": {"passports_all_11a": "8", "resident_age_8d": "4", "ns_sec_10a": "3"}}, {"count": 1564, "dims": {"passports_all_11a": "8", "resident_age_8d": "4", "ns_sec_10a": "4"}}, {"count": 559, "dims": {"passports_all_11a": "8", "resident_age_8d": "4", "ns_sec_10a": "5"}}, {"count": 700, "dims": {"passports_all_11a": "8", "resident_age_8d": "4", "ns_sec_10a": "6"}}, {"count": 465, "dims": {"passports_all_11a": "8", "resident_age_8d": "4", "ns_sec_10a": "7"}}, {"count": 403, "dims": {"passports_all_11a": "8", "resident_age_8d": "4", "ns_sec_10a": "8"}}, {"count": 171, "dims": {"passports_all_11a": "8", "resident_age_8d": "4", "ns_sec_10a": "9"}}, {"count": 0, "dims": {"passports_all_11a": "8", "resident_age_8d": "5", "ns_sec_10a": "-8"}}, {"count": 4275, "dims": {"passports_all_11a": "8", "resident_age_8d": "5", "ns_sec_10a": "1"}}, {"count": 3804, "dims": {"passports_all_11a": "8", "resident_age_8d": "5", "ns_sec_10a": "2"}}, {"count": 1191, "dims": {"passports_all_11a": "8", "resident_age_8d": "5", "ns_sec_10a": "3"}}, {"count": 1805, "dims": {"passports_all_11a": "8", "resident_age_8d": "5", "ns_sec_10a": "4"}}, {"count": 408, "dims": {"passports_all_11a": "8", "resident_age_8d": "5", "ns_sec_10a": "5"}}, {"count": 602, "dims": {"passports_all_11a": "8", "resident_age_8d": "5", "ns_sec_10a": "6"}}, {"count": 498, "dims": {"passports_all_11a": "8", "resident_age_8d": "5", "ns_sec_10a": "7"}}, {"count": 369, "dims": {"passports_all_11a": "8", "resident_age_8d": "5", "ns_sec_10a": "8"}}, {"count": 81, "dims": {"passports_all_11a": "8", "resident_age_8d": "5", "ns_sec_10a": "9"}}, {"count": 0, "dims": {"passports_all_11a": "8", "resident_age_8d": "6", "ns_sec_10a": "-8"}}, {"count": 1903, "dims": {"passports_all_11a": "8", "resident_age_8d": "6", "ns_sec_10a": "1"}}, {"count": 1973, "dims": {"passports_all_11a": "8", "resident_age_8d": "6", "ns_sec_10a": "2"}}, {"count": 671, "dims": {"passports_all_11a": "8", "resident_age_8d": "6", "ns_sec_10a": "3"}}, {"count": 1146, "dims": {"passports_all_11a": "8", "resident_age_8d": "6", "ns_sec_10a": "4"}}, {"count": 216, "dims": {"passports_all_11a": "8", "resident_age_8d": "6", "ns_sec_10a": "5"}}, {"count": 436, "dims": {"passports_all_11a": "8", "resident_age_8d": "6", "ns_sec_10a": "6"}}, {"count": 332, "dims": {"passports_all_11a": "8", "resident_age_8d": "6", "ns_sec_10a": "7"}}, {"count": 251, "dims": {"passports_all_11a": "8", "resident_age_8d": "6", "ns_sec_10a": "8"}}, {"count": 28, "dims": {"passports_all_11a": "8", "resident_age_8d": "6", "ns_sec_10a": "9"}}, {"count": 0, "dims": {"passports_all_11a": "8", "resident_age_8d": "7", "ns_sec_10a": "-8"}}, {"count": 897, "dims": {"passports_all_11a": "8", "resident_age_8d": "7", "ns_sec_10a": "1"}}, {"count": 1124, "dims": {"passports_all_11a": "8", "resident_age_8d": "7", "ns_sec_10a": "2"}}, {"count": 480, "dims": {"passports_all_11a": "8", "resident_age_8d": "7", "ns_sec_10a": "3"}}, {"count": 699, "dims": {"passports_all_11a": "8", "resident_age_8d": "7", "ns_sec_10a": "4"}}, {"count": 110, "dims": {"passports_all_11a": "8", "resident_age_8d": "7", "ns_sec_10a": "5"}}, {"count": 302, "dims": {"passports_all_11a": "8", "resident_age_8d": "7", "ns_sec_10a": "6"}}, {"count": 209, "dims": {"passports_all_11a": "8", "resident_age_8d": "7", "ns_sec_10a": "7"}}, {"count": 268, "dims": {"passports_all_11a": "8", "resident_age_8d": "7", "ns_sec_10a": "8"}}, {"count": 9, "dims": {"passports_all_11a": "8", "resident_age_8d": "7", "ns_sec_10a": "9"}}, {"count": 0, "dims": {"passports_all_11a": "8", "resident_age_8d": "8", "ns_sec_10a": "-8"}}, {"count": 440, "dims": {"passports_all_11a": "8", "resident_age_8d": "8", "ns_sec_10a": "1"}}, {"count": 695, "dims": {"passports_all_11a": "8", "resident_age_8d": "8", "ns_sec_10a": "2"}}, {"count": 263, "dims": {"passports_all_11a": "8", "resident_age_8d": "8", "ns_sec_10a": "3"}}, {"count": 331, "dims": {"passports_all_11a": "8", "resident_age_8d": "8", "ns_sec_10a": "4"}}, {"count": 57, "dims": {"passports_all_11a": "8", "resident_age_8d": "8", "ns_sec_10a": "5"}}, {"count": 144, "dims": {"passports_all_11a": "8", "resident_age_8d": "8", "ns_sec_10a": "6"}}, {"count": 122, "dims": {"passports_all_11a": "8", "resident_age_8d": "8", "ns_sec_10a": "7"}}, {"count": 197, "dims": {"passports_all_11a": "8", "resident_age_8d": "8", "ns_sec_10a": "8"}}, {"count": 5, "dims": {"passports_all_11a": "8", "resident_age_8d": "8", "ns_sec_10a": "9"}}, {"count": 151, "dims": {"passports_all_11a": "9", "resident_age_8d": "1", "ns_sec_10a": "-8"}}, {"count": 0, "dims": {"passports_all_11a": "9", "resident_age_8d": "1", "ns_sec_10a": "1"}}, {"count": 0, "dims": {"passports_all_11a": "9", "resident_age_8d": "1", "ns_sec_10a": "2"}}, {"count": 0, "dims": {"passports_all_11a": "9", "resident_age_8d": "1", "ns_sec_10a": "3"}}, {"count": 0, "dims": {"passports_all_11a": "9", "resident_age_8d": "1", "ns_sec_10a": "4"}}, {"count": 0, "dims": {"passports_all_11a": "9", "resident_age_8d": "1", "ns_sec_10a": "5"}}, {"count": 0, "dims": {"passports_all_11a": "9", "resident_age_8d": "1", "ns_sec_10a": "6"}}, {"count": 0, "dims": {"passports_all_11a": "9", "resident_age_8d": "1", "ns_sec_10a": "7"}}, {"count": 0, "dims": {"passports_all_11a": "9", "resident_age_8d": "1", "ns_sec_10a": "8"}}, {"count": 0, "dims": {"passports_all_11a": "9", "resident_age_8d": "1", "ns_sec_10a": "9"}}, {"count": 0, "dims": {"passports_all_11a": "9", "resident_age_8d": "2", "ns_sec_10a": "-8"}}, {"count": 1, "dims": {"passports_all_11a": "9", "resident_age_8d": "2", "ns_sec_10a": "1"}}, {"count": 4, "dims": {"passports_all_11a": "9", "resident_age_8d": "2", "ns_sec_10a": "2"}}, {"count": 6, "dims": {"passports_all_11a": "9", "resident_age_8d": "2", "ns_sec_10a": "3"}}, {"count": 3, "dims": {"passports_all_11a": "9", "resident_age_8d": "2", "ns_sec_10a": "4"}}, {"count": 2, "dims": {"passports_all_11a": "9", "resident_age_8d": "2", "ns_sec_10a": "5"}}, {"count": 7, "dims": {"passports_all_11a": "9", "resident_age_8d": "2", "ns_sec_10a": "6"}}, {"count": 13, "dims": {"passports_all_11a": "9", "resident_age_8d": "2", "ns_sec_10a": "7"}}, {"count": 18, "dims": {"passports_all_11a": "9", "resident_age_8d": "2", "ns_sec_10a": "8"}}, {"count": 80, "dims": {"passports_all_11a": "9", "resident_age_8d": "2", "ns_sec_10a": "9"}}, {"count": 0, "dims": {"passports_all_11a": "9", "resident_age_8d": "3", "ns_sec_10a": "-8"}}, {"count": 17, "dims": {"passports_all_11a": "9", "resident_age_8d": "3", "ns_sec_10a": "1"}}, {"count": 20, "dims": {"passports_all_11a": "9", "resident_age_8d": "3", "ns_sec_10a": "2"}}, {"count": 13, "dims": {"passports_all_11a": "9", "resident_age_8d": "3", "ns_sec_10a": "3"}}, {"count": 6, "dims": {"passports_all_11a": "9", "resident_age_8d": "3", "ns_sec_10a": "4"}}, {"count": 3, "dims": {"passports_all_11a": "9", "resident_age_8d": "3", "ns_sec_10a": "5"}}, {"count": 10, "dims": {"passports_all_11a": "9", "resident_age_8d": "3", "ns_sec_10a": "6"}}, {"count": 9, "dims": {"passports_all_11a": "9", "resident_age_8d": "3", "ns_sec_10a": "7"}}, {"count": 29, "dims": {"passports_all_11a": "9", "resident_age_8d": "3", "ns_sec_10a": "8"}}, {"count": 6, "dims": {"passports_all_11a": "9", "resident_age_8d": "3", "ns_sec_10a": "9"}}, {"count": 0, "dims": {"passports_all_11a": "9", "resident_age_8d": "4", "ns_sec_10a": "-8"}}, {"count": 10, "dims": {"passports_all_11a": "9", "resident_age_8d": "4", "ns_sec_10a": "1"}}, {"count": 18, "dims": {"passports_all_11a": "9", "resident_age_8d": "4", "ns_sec_10a": "2"}}, {"count": 9, "dims": {"passports_all_11a": "9", "resident_age_8d": "4", "ns_sec_10a": "3"}}, {"count": 19, "dims": {"passports_all_11a": "9", "resident_age_8d": "4", "ns_sec_10a": "4"}}, {"count": 6, "dims": {"passports_all_11a": "9", "resident_age_8d": "4", "ns_sec_10a": "5"}}, {"count": 8, "dims": {"passports_all_11a": "9", "resident_age_8d": "4", "ns_sec_10a": "6"}}, {"count": 13, "dims": {"passports_all_11a": "9", "resident_age_8d": "4", "ns_sec_10a": "7"}}, {"count": 21, "dims": {"passports_all_11a": "9", "resident_age_8d": "4", "ns_sec_10a": "8"}}, {"count": 1, "dims": {"passports_all_11a": "9", "resident_age_8d": "4", "ns_sec_10a": "9"}}, {"count": 0, "dims": {"passports_all_11a": "9", "resident_age_8d": "5", "ns_sec_10a": "-8"}}, {"count": 8, "dims": {"passports_all_11a": "9", "resident_age_8d": "5", "ns_sec_10a": "1"}}, {"count": 7, "dims": {"passports_all_11a": "9", "resident_age_8d": "5", "ns_sec_10a": "2"}}, {"count": 6, "dims": {"passports_all_11a": "9", "resident_age_8d": "5", "ns_sec_10a": "3"}}, {"count": 4, "dims": {"passports_all_11a": "9", "resident_age_8d": "5", "ns_sec_10a": "4"}}, {"count": 6, "dims": {"passports_all_11a": "9", "resident_age_8d": "5", "ns_sec_10a": "5"}}, {"count": 8, "dims": {"passports_all_11a": "9", "resident_age_8d": "5", "ns_sec_10a": "6"}}, {"count": 9, "dims": {"passports_all_11a": "9", "resident_age_8d": "5", "ns_sec_10a": "7"}}, {"count": 9, "dims": {"passports_all_11a": "9", "resident_age_8d": "5", "ns_sec_10a": "8"}}, {"count": 0, "dims": {"passports_all_11a": "9", "resident_age_8d": "5", "ns_sec_10a": "9"}}, {"count": 0, "dims": {"passports_all_11a": "9", "resident_age_8d": "6", "ns_sec_10a": "-8"}}, {"count": 5, "dims": {"passports_all_11a": "9", "resident_age_8d": "6", "ns_sec_10a": "1"}}, {"count": 7, "dims": {"passports_all_11a": "9", "resident_age_8d": "6", "ns_sec_10a": "2"}}, {"count": 6, "dims": {"passports_all_11a": "9", "resident_age_8d": "6", "ns_sec_10a": "3"}}, {"count": 8, "dims": {"passports_all_11a": "9", "resident_age_8d": "6", "ns_sec_10a": "4"}}, {"count": 3, "dims": {"passports_all_11a": "9", "resident_age_8d": "6", "ns_sec_10a": "5"}}, {"count": 3, "dims": {"passports_all_11a": "9", "resident_age_8d": "6", "ns_sec_10a": "6"}}, {"count": 9, "dims": {"passports_all_11a": "9", "resident_age_8d": "6", "ns_sec_10a": "7"}}, {"count": 10, "dims": {"passports_all_11a": "9", "resident_age_8d": "6", "ns_sec_10a": "8"}}, {"count": 0, "dims": {"passports_all_11a": "9", "resident_age_8d": "6", "ns_sec_10a": "9"}}, {"count": 0, "dims": {"passports_all_11a": "9", "resident_age_8d": "7", "ns_sec_10a": "-8"}}, {"count": 2, "dims": {"passports_all_11a": "9", "resident_age_8d": "7", "ns_sec_10a": "1"}}, {"count": 5, "dims": {"passports_all_11a": "9", "resident_age_8d": "7", "ns_sec_10a": "2"}}, {"count": 1, "dims": {"passports_all_11a": "9", "resident_age_8d": "7", "ns_sec_10a": "3"}}, {"count": 2, "dims": {"passports_all_11a": "9", "resident_age_8d": "7", "ns_sec_10a": "4"}}, {"count": 1, "dims": {"passports_all_11a": "9", "resident_age_8d": "7", "ns_sec_10a": "5"}}, {"count": 8, "dims": {"passports_all_11a": "9", "resident_age_8d": "7", "ns_sec_10a": "6"}}, {"count": 1, "dims": {"passports_all_11a": "9", "resident_age_8d": "7", "ns_sec_10a": "7"}}, {"count": 2, "dims": {"passports_all_11a": "9", "resident_age_8d": "7", "ns_sec_10a": "8"}}, {"count": 0, "dims": {"passports_all_11a": "9", "resident_age_8d": "7", "ns_sec_10a": "9"}}, {"count": 0, "dims": {"passports_all_11a": "9", "resident_age_8d": "8", "ns_sec_10a": "-8"}}, {"count": 2, "dims": {"passports_all_11a": "9", "resident_age_8d": "8", "ns_sec_10a": "1"}}, {"count": 2, "dims": {"passports_all_11a": "9", "resident_age_8d": "8", "ns_sec_10a": "2"}}, {"count": 1, "dims": {"passports_all_11a": "9", "resident_age_8d": "8", "ns_sec_10a": "3"}}, {"count": 1, "dims": {"passports_all_11a": "9", "resident_age_8d": "8", "ns_sec_10a": "4"}}, {"count": 0, "dims": {"passports_all_11a": "9", "resident_age_8d": "8", "ns_sec_10a": "5"}}, {"count": 1, "dims": {"passports_all_11a": "9", "resident_age_8d": "8", "ns_sec_10a": "6"}}, {"count": 0, "dims": {"passports_all_11a": "9", "resident_age_8d": "8", "ns_sec_10a": "7"}}, {"count": 1, "dims": {"passports_all_11a": "9", "resident_age_8d": "8", "ns_sec_10a": "8"}}, {"count": 0, "dims": {"passports_all_11a": "9", "resident_age_8d": "8", "ns_sec_10a": "9"}}, {"count": 2598769, "dims": {"passports_all_11a": "10", "resident_age_8d": "1", "ns_sec_10a": "-8"}}, {"count": 0, "dims": {"passports_all_11a": "10", "resident_age_8d": "1", "ns_sec_10a": "1"}}, {"count": 0, "dims": {"passports_all_11a": "10", "resident_age_8d": "1", "ns_sec_10a": "2"}}, {"count": 0, "dims": {"passports_all_11a": "10", "resident_age_8d": "1", "ns_sec_10a": "3"}}, {"count": 0, "dims": {"passports_all_11a": "10", "resident_age_8d": "1", "ns_sec_10a": "4"}}, {"count": 0, "dims": {"passports_all_11a": "10", "resident_age_8d": "1", "ns_sec_10a": "5"}}, {"count": 0, "dims": {"passports_all_11a": "10", "resident_age_8d": "1", "ns_sec_10a": "6"}}, {"count": 0, "dims": {"passports_all_11a": "10", "resident_age_8d": "1", "ns_sec_10a": "7"}}, {"count": 0, "dims": {"passports_all_11a": "10", "resident_age_8d": "1", "ns_sec_10a": "8"}}, {"count": 0, "dims": {"passports_all_11a": "10", "resident_age_8d": "1", "ns_sec_10a": "9"}}, {"count": 0, "dims": {"passports_all_11a": "10", "resident_age_8d": "2", "ns_sec_10a": "-8"}}, {"count": 3915, "dims": {"passports_all_11a": "10", "resident_age_8d": "2", "ns_sec_10a": "1"}}, {"count": 15216, "dims": {"passports_all_11a": "10", "resident_age_8d": "2", "ns_sec_10a": "2"}}, {"count": 20915, "dims": {"passports_all_11a": "10", "resident_age_8d": "2", "ns_sec_10a": "3"}}, {"count": 12420, "dims": {"passports_all_11a": "10", "resident_age_8d": "2", "ns_sec_10a": "4"}}, {"count": 16334, "dims": {"passports_all_11a": "10", "resident_age_8d": "2", "ns_sec_10a": "5"}}, {"count": 56095, "dims": {"passports_all_11a": "10", "resident_age_8d": "2", "ns_sec_10a": "6"}}, {"count": 68763, "dims": {"passports_all_11a": "10", "resident_age_8d": "2", "ns_sec_10a": "7"}}, {"count": 119649, "dims": {"passports_all_11a": "10", "resident_age_8d": "2", "ns_sec_10a": "8"}}, {"count": 223759, "dims": {"passports_all_11a": "10", "resident_age_8d": "2", "ns_sec_10a": "9"}}, {"count": 0, "dims": {"passports_all_11a": "10", "resident_age_8d": "3", "ns_sec_10a": "-8"}}, {"count": 14604, "dims": {"passports_all_11a": "10", "resident_age_8d": "3", "ns_sec_10a": "1"}}, {"count": 47610, "dims": {"passports_all_11a": "10", "resident_age_8d": "3", "ns_sec_10a": "2"}}, {"count": 40691, "dims": {"passports_all_11a": "10", "resident_age_8d": "3", "ns_sec_10a": "3"}}, {"count": 35696, "dims": {"passports_all_11a": "10", "resident_age_8d": "3", "ns_sec_10a": "4"}}, {"count": 33272, "dims": {"passports_all_11a": "10", "resident_age_8d": "3", "ns_sec_10a": "5"}}, {"count": 98794, "dims": {"passports_all_11a": "10", "resident_age_8d": "3", "ns_sec_10a": "6"}}, {"count": 111731, "dims": {"passports_all_11a": "10", "resident_age_8d": "3", "ns_sec_10a": "7"}}, {"count": 146708, "dims": {"passports_all_11a": "10", "resident_age_8d": "3", "ns_sec_10a": "8"}}, {"count": 13628, "dims": {"passports_all_11a": "10", "resident_age_8d": "3", "ns_sec_10a": "9"}}, {"count": 0, "dims": {"passports_all_11a": "10", "resident_age_8d": "4", "ns_sec_10a": "-8"}}, {"count": 20916, "dims": {"passports_all_11a": "10", "resident_age_8d": "4", "ns_sec_10a": "1"}}, {"count": 60222, "dims": {"passports_all_11a": "10", "resident_age_8d": "4", "ns_sec_10a": "2"}}, {"count": 46439, "dims": {"passports_all_11a": "10", "resident_age_8d": "4", "ns_sec_10a": "3"}}, {"count": 47604, "dims": {"passports_all_11a": "10", "resident_age_8d": "4", "ns_sec_10a": "4"}}, {"count": 37537, "dims": {"passports_all_11a": "10", "resident_age_8d": "4", "ns_sec_10a": "5"}}, {"count": 91792, "dims": {"passports_all_11a": "10", "resident_age_8d": "4", "ns_sec_10a": "6"}}, {"count": 114818, "dims": {"passports_all_11a": "10", "resident_age_8d": "4", "ns_sec_10a": "7"}}, {"count": 118264, "dims": {"passports_all_11a": "10", "resident_age_8d": "4", "ns_sec_10a": "8"}}, {"count": 6976, "dims": {"passports_all_11a": "10", "resident_age_8d": "4", "ns_sec_10a": "9"}}, {"count": 0, "dims": {"passports_all_11a": "10", "resident_age_8d": "5", "ns_sec_10a": "-8"}}, {"count": 26669, "dims": {"passports_all_11a": "10", "resident_age_8d": "5", "ns_sec_10a": "1"}}, {"count": 76014, "dims": {"passports_all_11a": "10", "resident_age_8d": "5", "ns_sec_10a": "2"}}, {"count": 62248, "dims": {"passports_all_11a": "10", "resident_age_8d": "5", "ns_sec_10a": "3"}}, {"count": 67577, "dims": {"passports_all_11a": "10", "resident_age_8d": "5", "ns_sec_10a": "4"}}, {"count": 49250, "dims": {"passports_all_11a": "10", "resident_age_8d": "5", "ns_sec_10a": "5"}}, {"count": 118656, "dims": {"passports_all_11a": "10", "resident_age_8d": "5", "ns_sec_10a": "6"}}, {"count": 159730, "dims": {"passports_all_11a": "10", "resident_age_8d": "5", "ns_sec_10a": "7"}}, {"count": 129676, "dims": {"passports_all_11a": "10", "resident_age_8d": "5", "ns_sec_10a": "8"}}, {"count": 3628, "dims": {"passports_all_11a": "10", "resident_age_8d": "5", "ns_sec_10a": "9"}}, {"count": 0, "dims": {"passports_all_11a": "10", "resident_age_8d": "6", "ns_sec_10a": "-8"}}, {"count": 27614, "dims": {"passports_all_11a": "10", "resident_age_8d": "6", "ns_sec_10a": "1"}}, {"count": 78395, "dims": {"passports_all_11a": "10", "resident_age_8d": "6", "ns_sec_10a": "2"}}, {"count": 72386, "dims": {"passports_all_11a": "10", "resident_age_8d": "6", "ns_sec_10a": "3"}}, {"count": 85107, "dims": {"passports_all_11a": "10", "resident_age_8d": "6", "ns_sec_10a": "4"}}, {"count": 55321, "dims": {"passports_all_11a": "10", "resident_age_8d": "6", "ns_sec_10a": "5"}}, {"count": 142190, "dims": {"passports_all_11a": "10", "resident_age_8d": "6", "ns_sec_10a": "6"}}, {"count": 199212, "dims": {"passports_all_11a": "10", "resident_age_8d": "6", "ns_sec_10a": "7"}}, {"count": 136655, "dims": {"passports_all_11a": "10", "resident_age_8d": "6", "ns_sec_10a": "8"}}, {"count": 1998, "dims": {"passports_all_11a": "10", "resident_age_8d": "6", "ns_sec_10a": "9"}}, {"count": 0, "dims": {"passports_all_11a": "10", "resident_age_8d": "7", "ns_sec_10a": "-8"}}, {"count": 33935, "dims": {"passports_all_11a": "10", "resident_age_8d": "7", "ns_sec_10a": "1"}}, {"count": 92994, "dims": {"passports_all_11a": "10", "resident_age_8d": "7", "ns_sec_10a": "2"}}, {"count": 85969, "dims": {"passports_all_11a": "10", "resident_age_8d": "7", "ns_sec_10a": "3"}}, {"count": 88899, "dims": {"passports_all_11a": "10", "resident_age_8d": "7", "ns_sec_10a": "4"}}, {"count": 61689, "dims": {"passports_all_11a": "10", "resident_age_8d": "7", "ns_sec_10a": "5"}}, {"count": 145745, "dims": {"passports_all_11a": "10", "resident_age_8d": "7", "ns_sec_10a": "6"}}, {"count": 198424, "dims": {"passports_all_11a": "10", "resident_age_8d": "7", "ns_sec_10a": "7"}}, {"count": 159370, "dims": {"passports_all_11a": "10", "resident_age_8d": "7", "ns_sec_10a": "8"}}, {"count": 1122, "dims": {"passports_all_11a": "10", "resident_age_8d": "7", "ns_sec_10a": "9"}}, {"count": 0, "dims": {"passports_all_11a": "10", "resident_age_8d": "8", "ns_sec_10a": "-8"}}, {"count": 63672, "dims": {"passports_all_11a": "10", "resident_age_8d": "8", "ns_sec_10a": "1"}}, {"count": 179240, "dims": {"passports_all_11a": "10", "resident_age_8d": "8", "ns_sec_10a": "2"}}, {"count": 170671, "dims": {"passports_all_11a": "10", "resident_age_8d": "8", "ns_sec_10a": "3"}}, {"count": 123492, "dims": {"passports_all_11a": "10", "resident_age_8d": "8", "ns_sec_10a": "4"}}, {"count": 102570, "dims": {"passports_all_11a": "10", "resident_age_8d": "8", "ns_sec_10a": "5"}}, {"count": 234170, "dims": {"passports_all_11a": "10", "resident_age_8d": "8", "ns_sec_10a": "6"}}, {"count": 290404, "dims": {"passports_all_11a": "10", "resident_age_8d": "8", "ns_sec_10a": "7"}}, {"count": 270307, "dims": {"passports_all_11a": "10", "resident_age_8d": "8", "ns_sec_10a": "8"}}, {"count": 1544, "dims": {"passports_all_11a": "10", "resident_age_8d": "8", "ns_sec_10a": "9"}}]}